{
  "sha256": "04739bba7ef80f72f47dd22eb66b9fddb6f48b5c3744b1f9cc6018615aa11bd6",
  "prompt_version": "v3",
  "iterations": [
    {
      "iteration": 0,
      "prompt_version": "v3",
      "yara_rule": "rule Bypass_Sample\n{\n    meta:\n        description = \"Evasion bypass rule\"\n        cape_options = \"bp0=$pattern0+0,action0=skip,bp1=$pattern1+0,action1=skip,bp2=$pattern2+0,action2=skip,count=0\"\n\n    strings:\n        $pattern0 = { 85 C0 74 0E E8 43 1C 00 00 }\n        $pattern1 = { E8 89 E0 FF FF 85 C0 }\n        $pattern2 = { 85 C0 74 0E E8 E0 A2 FF FF }\n\n    condition:\n        any of them\n}",
      "pattern_type": "UNKNOWN",
      "confidence": 50,
      "opcodes": "",
      "task_id": "1221",
      "status": "rule_hit",
      "rule_hit": true,
      "baseline_signatures": 22,
      "new_signatures": 0,
      "new_signature_names": [],
      "new_signature_details": [],
      "failure_reason": "Rule hit but no new signatures",
      "improvement_suggestions": [
        "Instead of fixed skip offsets, try a more dynamic approach.  The goal is to skip the initial instruction sequence while allowing the program to continue execution.  A better approach is to skip to the"
      ],
      "debugger_log": "=== 1852.log ===\nCAPE Sandbox - Debugger log: Sat Dec 20 15:32:10 2025\nBreakpoint 1 hit by instruction at 0x00421412 (thread 7840) EAX=0x76e83f10 GetKeyboardLayoutList  EBX=0xb24000 ECX=0xb27000 EDX=0xc0000141 EDI=0x40717b ESP=0xcff798 *ESP=0xcff828 EBP=0xcff798\nBreak at 0x00421412 in 04739bba7ef80f72f47d.exe (RVA 0x21412, thread 7840, Stack 0x00CF2000-0x00D00000, ImageBase 0x00400000)\n0x00421412  E889E0FFFF               CALL      0xffffe08e                    \nActionDispatcher: skipping instruction.\n0x00421417  85C0                     TEST      EAX, EAX                      \n",
      "raw_response": "```yara\nrule Bypass_Sample\n{\n    meta:\n        description = \"Evasion bypass rule\"\n        cape_options = \"bp0=$pattern0+0,action0=skip,bp1=$pattern1+0,action1=skip,bp2=$pattern2+0,action2=skip,count=0\"\n\n    strings:\n        $pattern0 = { 85 C0 74 0E E8 43 1C 00 00 }\n        $pattern1 = { E8 89 E0 FF FF 85 C0 }\n        $pattern2 = { 85 C0 74 0E E8 E0 A2 FF FF }\n\n    condition:\n        any of them\n}\n```",
      "yara_file": "ablation_results\\gemma3_12b\\Iter\\Iter\\04739bba7ef80f72\\iter0_v3.yar"
    },
    {
      "iteration": 1,
      "prompt_version": "v3",
      "yara_rule": "rule Bypass_Sample_Evolved\n{\n    meta:\n        description = \"Evasion bypass rule - evolved\"\n        cape_options = \"bp0=$pattern0+0,action0=skip,bp1=$pattern1+0,action1=skip,bp2=$pattern2+0,action2=skip,count=0\"\n\n    strings:\n        $pattern0 = { E8 EE 82 FF FF 85 C0 74 0E }\n        $pattern1 = { E8 89 E0 FF FF 85 C0 74 0E }\n        $pattern2 = { E8 B7 F7 FF FF 85 C0 74 0E }\n\n    condition:\n        any of them\n}",
      "pattern_type": "UNKNOWN",
      "confidence": 50,
      "opcodes": "",
      "task_id": "1222",
      "status": "rule_hit",
      "rule_hit": true,
      "baseline_signatures": 22,
      "new_signatures": 0,
      "new_signature_names": [],
      "new_signature_details": [],
      "failure_reason": "Rule hit but no new signatures",
      "improvement_suggestions": [
        "Instead of skipping the `CALL` instruction directly, target a more robust and less critical instruction within the sequence. The `TEST EAX, EAX` instruction seems relatively safe to skip as it's a no-op in this context. Furthermore, avoid fixed skip offsets and allow the engine to dynamically adjust based on the context."
      ],
      "debugger_log": "=== 2512.log ===\nCAPE Sandbox - Debugger log: Sat Dec 20 14:58:57 2025\nBreakpoint 1 hit by instruction at 0x00421412 (thread 2624) EAX=0x76e83f10 GetKeyboardLayoutList  EBX=0xf54000 ECX=0xf57000 EDX=0xc0000141 EDI=0x40717b ESP=0x10ffccc *ESP=0x10ffd5c EBP=0x10ffccc\nBreak at 0x00421412 in 04739bba7ef80f72f47d.exe (RVA 0x21412, thread 2624, Stack 0x010F2000-0x01100000, ImageBase 0x00400000)\n0x00421412  E889E0FFFF               CALL      0xffffe08e                    \nActionDispatcher: skipping instruction.\n0x00421417  85C0                     TEST      EAX, EAX                      \n",
      "raw_response": "```yara\nrule Bypass_Sample_Evolved\n{\n    meta:\n        description = \"Evasion bypass rule - evolved\"\n        cape_options = \"bp0=$pattern0+0,action0=skip,bp1=$pattern1+0,action1=skip,bp2=$pattern2+0,action2=skip,count=0\"\n\n    strings:\n        $pattern0 = { E8 EE 82 FF FF 85 C0 74 0E }\n        $pattern1 = { E8 89 E0 FF FF 85 C0 74 0E }\n        $pattern2 = { E8 B7 F7 FF FF 85 C0 74 0E }\n\n    condition:\n        any of them\n}\n```",
      "yara_file": "ablation_results\\gemma3_12b\\Iter\\Iter\\04739bba7ef80f72\\iter1_v3.yar"
    },
    {
      "iteration": 2,
      "prompt_version": "v3",
      "yara_rule": "rule Bypass_Sample_Evolved\n{\n    meta:\n        description = \"Evasion bypass rule - evolved\"\n        cape_options = \"bp0=$pattern0+0,action0=skip,bp1=$pattern1+0,action1=skip,bp2=$pattern2+0,action2=skip,count=0\"\n\n    strings:\n        $pattern0 = { E8 43 1C 00 00 E8 EE 82 FF FF }\n        $pattern1 = { E8 89 E0 FF FF 85 C0 74 0E }\n        $pattern2 = { 85 C0 E8 E0 A2 FF FF 85 C0 74 0E }\n\n    condition:\n        any of them\n}",
      "pattern_type": "UNKNOWN",
      "confidence": 50,
      "opcodes": "",
      "task_id": "1223",
      "status": "bypass_success",
      "rule_hit": true,
      "baseline_signatures": 22,
      "new_signatures": 1,
      "new_signature_names": [
        "terminates_remote_process"
      ],
      "new_signature_details": [
        {
          "name": "terminates_remote_process",
          "description": "Terminates another process",
          "categories": [
            "persistence",
            "stealth"
          ],
          "severity": 2,
          "weight": 1,
          "confidence": 100,
          "references": [],
          "data": [
            {
              "type": "call",
              "pid": 7720,
              "cid": 21861
            },
            {
              "process": "04739bba7ef80f72f47d.exe"
            }
          ],
          "new_data": [],
          "alert": false,
          "families": []
        }
      ],
      "failure_reason": null,
      "improvement_suggestions": [],
      "debugger_log": "=== 9132.log ===\nCAPE Sandbox - Debugger log: Sat Dec 20 14:05:48 2025\nBreakpoint 0 hit by instruction at 0x00421408 (thread 9180) EAX=0xf13362 EBX=0xb0b000 ECX=0x4326f8 EDX=0x4 EDI=0x40717b ESP=0xd3f978 *ESP=0xd3fa08 EBP=0xd3f978\nBreak at 0x00421408 in 04739bba7ef80f72f47d.exe (RVA 0x21408, thread 9180, Stack 0x00D32000-0x00D40000, ImageBase 0x00400000)\n0x00421408  E8431C0000               CALL      0x1c48                        \nActionDispatcher: skipping instruction.\n0x0042140D  E8EE82FFFF               CALL      0x00419700                    \n",
      "raw_response": "```yara\nrule Bypass_Sample_Evolved\n{\n    meta:\n        description = \"Evasion bypass rule - evolved\"\n        cape_options = \"bp0=$pattern0+0,action0=skip,bp1=$pattern1+0,action1=skip,bp2=$pattern2+0,action2=skip,count=0\"\n\n    strings:\n        $pattern0 = { E8 43 1C 00 00 E8 EE 82 FF FF }\n        $pattern1 = { E8 89 E0 FF FF 85 C0 74 0E }\n        $pattern2 = { 85 C0 E8 E0 A2 FF FF 85 C0 74 0E }\n\n    condition:\n        any of them\n}\n```",
      "yara_file": "ablation_results\\gemma3_12b\\Iter\\Iter\\04739bba7ef80f72\\iter2_v3.yar"
    }
  ],
  "best_attempt": {
    "iteration": 2,
    "prompt_version": "v3",
    "yara_rule": "rule Bypass_Sample_Evolved\n{\n    meta:\n        description = \"Evasion bypass rule - evolved\"\n        cape_options = \"bp0=$pattern0+0,action0=skip,bp1=$pattern1+0,action1=skip,bp2=$pattern2+0,action2=skip,count=0\"\n\n    strings:\n        $pattern0 = { E8 43 1C 00 00 E8 EE 82 FF FF }\n        $pattern1 = { E8 89 E0 FF FF 85 C0 74 0E }\n        $pattern2 = { 85 C0 E8 E0 A2 FF FF 85 C0 74 0E }\n\n    condition:\n        any of them\n}",
    "pattern_type": "UNKNOWN",
    "confidence": 50,
    "opcodes": "",
    "task_id": "1223",
    "status": "bypass_success",
    "rule_hit": true,
    "baseline_signatures": 22,
    "new_signatures": 1,
    "new_signature_names": [
      "terminates_remote_process"
    ],
    "new_signature_details": [
      {
        "name": "terminates_remote_process",
        "description": "Terminates another process",
        "categories": [
          "persistence",
          "stealth"
        ],
        "severity": 2,
        "weight": 1,
        "confidence": 100,
        "references": [],
        "data": [
          {
            "type": "call",
            "pid": 7720,
            "cid": 21861
          },
          {
            "process": "04739bba7ef80f72f47d.exe"
          }
        ],
        "new_data": [],
        "alert": false,
        "families": []
      }
    ],
    "failure_reason": null,
    "improvement_suggestions": [],
    "debugger_log": "=== 9132.log ===\nCAPE Sandbox - Debugger log: Sat Dec 20 14:05:48 2025\nBreakpoint 0 hit by instruction at 0x00421408 (thread 9180) EAX=0xf13362 EBX=0xb0b000 ECX=0x4326f8 EDX=0x4 EDI=0x40717b ESP=0xd3f978 *ESP=0xd3fa08 EBP=0xd3f978\nBreak at 0x00421408 in 04739bba7ef80f72f47d.exe (RVA 0x21408, thread 9180, Stack 0x00D32000-0x00D40000, ImageBase 0x00400000)\n0x00421408  E8431C0000               CALL      0x1c48                        \nActionDispatcher: skipping instruction.\n0x0042140D  E8EE82FFFF               CALL      0x00419700                    \n",
    "raw_response": "```yara\nrule Bypass_Sample_Evolved\n{\n    meta:\n        description = \"Evasion bypass rule - evolved\"\n        cape_options = \"bp0=$pattern0+0,action0=skip,bp1=$pattern1+0,action1=skip,bp2=$pattern2+0,action2=skip,count=0\"\n\n    strings:\n        $pattern0 = { E8 43 1C 00 00 E8 EE 82 FF FF }\n        $pattern1 = { E8 89 E0 FF FF 85 C0 74 0E }\n        $pattern2 = { 85 C0 E8 E0 A2 FF FF 85 C0 74 0E }\n\n    condition:\n        any of them\n}\n```",
    "yara_file": "ablation_results\\gemma3_12b\\Iter\\Iter\\04739bba7ef80f72\\iter2_v3.yar"
  },
  "best_score": 1,
  "optimization_history": [
    "Iteration 1: rule_hit - Rule hit but no new signatures",
    "Iteration 2: rule_hit - Rule hit but no new signatures",
    "Iteration 3: SUCCESS - 1 new signatures"
  ],
  "successful_patterns": [
    ""
  ],
  "failed_patterns": [
    "",
    ""
  ]
}