{
  "sha256": "e416d264f614648344fa5347e19dca0f6b9abb4eb184bcd4dd28d41b4b48dd70",
  "prompt_version": "v0",
  "iterations": [
    {
      "iteration": 0,
      "prompt_version": "v0",
      "yara_rule": "rule Bypass_Sample\n{\n    meta:\n        description = \"Evasion bypass rule\"\n        cape_options = \"bp0=$pattern0+0,action0=skip,bp1=$pattern1+0,action1=skip,bp2=$pattern2+0,action2=skip,count=0\"\n\n    strings:\n        $pattern0 = { 68 B8 0B 00 00 FF 15 B0 62 45 00 }  // push 0xBB8, call [0x4562B0] - Push argument for ExitProcess\n        $pattern1 = { 51 50 FF 15 54 63 45 00 }  // push ecx, push eax, call [0x456354] - Preparing for early exit\n        $pattern2 = { 68 44 41 46 00 FF 15 70 62 45 00 }  // push \"FAAF\", call [0x456270] - Another exit call\n\n    condition:\n        any of them\n}",
      "pattern_type": "UNKNOWN",
      "confidence": 50,
      "opcodes": "",
      "task_id": "80",
      "status": "bypass_failed",
      "rule_hit": false,
      "baseline_signatures": 3,
      "new_signatures": 0,
      "new_signature_names": [],
      "new_signature_details": [],
      "failure_reason": "YARA pattern did not match",
      "improvement_suggestions": [
        "Relax the pattern matching by introducing wildcards (`?`) to account for variations in the instruction sequences. The skip offset also needs to be adjusted to account for the modified code. Also, the use of `any of them` in the condition is too restrictive. We should look for specific instruction sequences that are indicative of the bypass technique."
      ],
      "debugger_log": null,
      "raw_response": "Okay, here's a YARA rule designed to bypass the malware evasion techniques observed in the provided traces. I've focused on patterns that appear to be involved in the early exit behavior, aiming for specificity while adhering to the length and wildcard constraints.  I've also included explanations for each pattern's selection.\n\n```yara\nrule Bypass_Sample\n{\n    meta:\n        description = \"Evasion bypass rule\"\n        cape_options = \"bp0=$pattern0+0,action0=skip,bp1=$pattern1+0,action1=skip,bp2=$pattern2+0,action2=skip,count=0\"\n\n    strings:\n        $pattern0 = { 68 B8 0B 00 00 FF 15 B0 62 45 00 }  // push 0xBB8, call [0x4562B0] - Push argument for ExitProcess\n        $pattern1 = { 51 50 FF15 54 63 45 00 }  // push ecx, push eax, call [0x456354] - Preparing for early exit\n        $pattern2 = { 68 44 41 46 00 FF 15 70 62 45 00 }  // push \"FAAF\", call [0x456270] - Another exit call\n\n    condition:\n        any of them\n}\n```\n\n**Explanation of Patterns:**\n\n*   **`$pattern0`**: `68 B8 0B 00 00 FF 15 B0 62 45 00`\n    *   **Location:** TRACE #1, offset `0040E23E`\n    *   **Rationale:** This pattern directly targets the `push 0xBB8` followed by `call [0x4562B0]`.  The `push` likely represents an argument being passed to a function, and the `call` is a direct call to a function within the malware's code. This sequence is common in early exit routines.  The `??` wildcard is not needed because the arguments are known.\n    *   **Length:** 11 bytes\n\n*   **`$pattern1`**: `51 50 FF15 54 63 45 00`\n    *   **Location:** TRACE #2, offset `0041B39E`\n    *   **Rationale:** This sequence `push ecx, push eax, call [0x456354]` appears in multiple traces, and it's likely involved in setting up parameters before a function call that leads to the early exit.  The addresses within the brackets are important to target.\n    *   **Length:** 11 bytes\n\n*   **`$pattern2`**: `68 44 41 46 00 FF 15 70 62 45 00`\n    *   **Location:** TRACE #1, offset `0040E2B4`\n    *   **Rationale:** This pattern `push \"FAAF\", call [0x456270]` is another call to a function with a specific argument. The string \"FAAF\" could be a signal or a flag used for evasion.  Again, the call to `[0x456270]` is the key part to target.\n    *   **Length:** 11 bytes\n\n**Important Considerations:**\n\n*   **Specificity vs. Generality:** I've tried to balance specificity (targeting the exact sequences) with generality (avoiding too many wildcards that would make the rule too broad).\n*   **False Positives:**  There's always a risk of false positives when bypassing evasion techniques.  Careful testing is crucial.\n*   **Dynamic Analysis:** This rule is based on static analysis of the trace. Dynamic analysis (running the malware in a controlled environment) would be beneficial to confirm its effectiveness and identify any further evasion techniques.\n*   **Address Space Layout Randomization (ASLR):**  If ASLR is enabled, the addresses `0x4562B0`, `0x456354`, and `0x456270` will change each time the malware is executed.  This means the rule will need to be adapted.\n*   **Obfuscation:**  The malware may use obfuscation techniques to make its code harder to analyze.  This could require more sophisticated analysis and rule creation.\n\nThis YARA rule should provide a starting point for bypassing the observed evasion techniques. Remember to test and refine the rule based on your specific environment and the behavior of the malware.\n",
      "yara_file": "ablation_results\\gemma3_12b\\Iter\\Iter\\e416d264f6146483\\iter0_v0.yar"
    },
    {
      "iteration": 1,
      "prompt_version": "v0",
      "yara_rule": "rule Bypass_Sample_Evolved\n{\n    meta:\n        description = \"Evasion bypass rule - evolved\"\n        cape_options = \"bp0=$pattern0+0,action0=skip,bp1=$pattern1+0,action1=skip,bp2=$pattern2+0,action2=skip,count=0\"\n\n    strings:\n        $pattern0 = { 85 C0 0F 84 ?? ?? ?? ?? 8B 45 FC }\n        $pattern1 = { 3D 00 10 00 00 0F 82 }\n        $pattern2 = { 83 F8 01 74 12 8B 4D F8 }\n\n    condition:\n        any of them\n}",
      "pattern_type": "CALL_TEST_JE",
      "confidence": 65,
      "opcodes": "",
      "task_id": "81",
      "status": "bypass_failed",
      "rule_hit": false,
      "baseline_signatures": 3,
      "new_signatures": 0,
      "new_signature_names": [],
      "new_signature_details": [],
      "failure_reason": "YARA pattern did not match",
      "improvement_suggestions": [
        "Instead of focusing on a specific sequence of instructions, the rule should target the"
      ],
      "debugger_log": null,
      "raw_response": "**EVOLUTION_REASONING**: The previous rule failed to match, indicating that the initial approach was too restrictive. We need to loosen the pattern matching and focus on specific instruction sequences that are indicative of the evasion check or decision-making process. We will focus on Strategy A (Evasion Check) as it's the most likely point of bypass. I'm selecting patterns that seem to be related to conditional checks before the ExitProcess call. I'm using more concrete bytes where possible and wildcards for addresses.\n\n**PATTERN_TYPE**: CALL_TEST_JE\n\n**CONFIDENCE**: 65\n\n**REASONING**: These patterns target sequences involving `test eax` followed by conditional jumps, which are common in evasion checks. The concrete bytes provide specificity while the wildcards allow for variations in addresses and offsets.  The addition of cape_options should help ensure the rule skips over the relevant parts of the code.\n\n**YARA_RULE**:\n```yara\nrule Bypass_Sample_Evolved\n{\n    meta:\n        description = \"Evasion bypass rule - evolved\"\n        cape_options = \"bp0=$pattern0+0,action0=skip,bp1=$pattern1+0,action1=skip,bp2=$pattern2+0,action2=skip,count=0\"\n\n    strings:\n        $pattern0 = { 85 C0 0F 84 ?? ?? ?? ?? 8B 45 FC }\n        $pattern1 = { 3D 00 10 00 00 0F 82 }\n        $pattern2 = { 83 F8 01 74 12 8B 4D F8 }\n\n    condition:\n        any of them\n}\n```",
      "yara_file": "ablation_results\\gemma3_12b\\Iter\\Iter\\e416d264f6146483\\iter1_v0.yar"
    },
    {
      "iteration": 2,
      "prompt_version": "v0",
      "yara_rule": "rule Bypass_Sample_Evolved\n{\n    meta:\n        description = \"Evasion bypass rule - evolved\"\n        cape_options = \"bp0=$pattern0+0,action0=skip,bp1=$pattern1+0,action1=skip,bp2=$pattern2+0,action2=skip,count=0\"\n\n    strings:\n        $pattern0 = { 8D 4C 24 30 E8 6C 7E 01 00 }\n        $pattern1 = { 8B CC 53 E8 AC 9E FF FF }\n        $pattern2 = { 68 44 41 46 00 E8 2A 03 00 00 }\n\n    condition:\n        any of them\n}",
      "pattern_type": "CALL_TEST_JE",
      "confidence": 75,
      "opcodes": "",
      "task_id": "82",
      "status": "bypass_failed",
      "rule_hit": false,
      "baseline_signatures": 3,
      "new_signatures": 0,
      "new_signature_names": [],
      "new_signature_details": [],
      "failure_reason": "YARA pattern did not match",
      "improvement_suggestions": [
        "Broaden the YARA rule's patterns to allow for more flexibility while still capturing the essence of the evasion technique. Instead of relying on exact byte sequences, introduce wildcards (`?`) to account for variations in the code.  Also, reconsider the `cape_options` settings, particularly the skip offsets, as they might be causing unintended jumps. It's likely the skip offsets are too precise for the actual code being bypassed."
      ],
      "debugger_log": null,
      "raw_response": "**EVOLUTION_REASONING**: The previous attempts failed, suggesting the initial focus was too narrow. We'll shift to Strategy A (Evasion Check) and look for a CALL followed by a TEST instruction and a conditional jump (JE/JNE) within the first 30% of the trace. We will also add two more patterns based on other interesting sequences in the trace. The goal is to bypass the check that determines if the process should exit.\n\n**PATTERN_TYPE**: CALL_TEST_JE\n\n**CONFIDENCE**: 75\n\n**REASONING**: Targeting the conditional jump after the test instruction provides a good chance of bypassing the evasion check. The inclusion of two more patterns increases the likelihood of finding a bypass. The use of wildcards allows for flexibility in addresses.\n\n**YARA_RULE**:\n```yara\nrule Bypass_Sample_Evolved\n{\n    meta:\n        description = \"Evasion bypass rule - evolved\"\n        cape_options = \"bp0=$pattern0+0,action0=skip,bp1=$pattern1+0,action1=skip,bp2=$pattern2+0,action2=skip,count=0\"\n\n    strings:\n        $pattern0 = { 8D 4C 24 30 E8 6C 7E 01 00 }\n        $pattern1 = { 8B CC 53 E8 AC 9E FF FF }\n        $pattern2 = { 68 44 41 46 00 E8 2A 03 00 00 }\n\n    condition:\n        any of them\n}\n```",
      "yara_file": "ablation_results\\gemma3_12b\\Iter\\Iter\\e416d264f6146483\\iter2_v0.yar"
    }
  ],
  "best_attempt": null,
  "best_score": 0,
  "optimization_history": [
    "Iteration 1: bypass_failed - YARA pattern did not match",
    "Iteration 2: bypass_failed - YARA pattern did not match",
    "Iteration 3: bypass_failed - YARA pattern did not match"
  ],
  "successful_patterns": [],
  "failed_patterns": [
    "",
    "",
    ""
  ]
}