{
  "sha256": "8cd1795a98c9fc8a17715b7c07b1658d62105370af020682ca38eb1665df2d7d",
  "prompt_version": "v1",
  "iterations": [
    {
      "iteration": 0,
      "prompt_version": "v1",
      "yara_rule": "rule Bypass_Sample\n{\n    meta:\n        description = \"Evasion bypass rule\"\n        cape_options = \"bp0=$pattern0+0,action0=skip,bp1=$pattern1+0,action1=skip,bp2=$pattern2+0,action2=skip,count=0\"\n\n    strings:\n        $pattern0 = { 20 74 20 85 C0 0F 84 ?? ?? ?? ?? E8 F7 25 00 00 }\n        $pattern1 = { 20 FF EE CE A8 01 8B 45 ?? FF 15 A0 F1 42 00 }\n        $pattern2 = { 20 FF EE CE FF 15 CF 14 20 00 50 FF 35 C0 F1 42 00 }\n\n    condition:\n        any of them\n}",
      "pattern_type": "UNKNOWN",
      "confidence": 50,
      "opcodes": "",
      "task_id": "1948",
      "status": "bypass_success",
      "rule_hit": true,
      "baseline_signatures": 26,
      "new_signatures": 4,
      "new_signature_names": [
        "process_interest",
        "antisandbox_unhook",
        "reads_memory_remote_process",
        "enumerates_running_processes"
      ],
      "new_signature_details": [
        {
          "name": "reads_memory_remote_process",
          "description": "Reads from the memory of another process",
          "categories": [
            "memory scraping",
            "injection"
          ],
          "severity": 2,
          "weight": 1,
          "confidence": 100,
          "references": [],
          "data": [
            {
              "read_memory": "Process microsoftedgeupdate.exe with process ID 6344 read from the memory of process handle 0x00000354"
            },
            {
              "type": "call",
              "pid": 6344,
              "cid": 1642
            },
            {
              "type": "call",
              "pid": 6344,
              "cid": 1643
            },
            {
              "type": "call",
              "pid": 6344,
              "cid": 1644
            }
          ],
          "new_data": [],
          "alert": false,
          "families": []
        },
        {
          "name": "enumerates_running_processes",
          "description": "Enumerates running processes",
          "categories": [
            "discovery"
          ],
          "severity": 2,
          "weight": 1,
          "confidence": 100,
          "references": [],
          "data": [
            {
              "process": "System with pid 4"
            },
            {
              "type": "call",
              "pid": 6344,
              "cid": 1068
            },
            {
              "process": "Registry with pid 92"
            },
            {
              "type": "call",
              "pid": 6344,
              "cid": 1069
            },
            {
              "process": "smss.exe with pid 336"
            },
            {
              "type": "call",
              "pid": 6344,
              "cid": 1070
            },
            {
              "process": "csrss.exe with pid 448"
            },
            {
              "type": "call",
              "pid": 6344,
              "cid": 1071
            },
            {
              "process": "wininit.exe with pid 524"
            },
            {
              "type": "call",
              "pid": 6344,
              "cid": 1072
            },
            {
              "process": "csrss.exe with pid 536"
            },
            {
              "type": "call",
              "pid": 6344,
              "cid": 1073
            },
            {
              "process": "winlogon.exe with pid 616"
            },
            {
              "type": "call",
              "pid": 6344,
              "cid": 1074
            },
            {
              "process": "services.exe with pid 656"
            },
            {
              "type": "call",
              "pid": 6344,
              "cid": 1075
            },
            {
              "process": "lsass.exe with pid 680"
            },
            {
              "type": "call",
              "pid": 6344,
              "cid": 1076
            },
            {
              "process": "svchost.exe with pid 776"
            },
            {
              "type": "call",
              "pid": 6344,
              "cid": 1077
            },
            {
              "process": "fontdrvhost.exe with pid 808"
            },
            {
              "type": "call",
              "pid": 6344,
              "cid": 1078
            },
            {
              "process": "fontdrvhost.exe with pid 816"
            },
            {
              "type": "call",
              "pid": 6344,
              "cid": 1079
            },
            {
              "process": "svchost.exe with pid 896"
            },
            {
              "type": "call",
              "pid": 6344,
              "cid": 1080
            },
            {
              "process": "svchost.exe with pid 956"
            },
            {
              "type": "call",
              "pid": 6344,
              "cid": 1081
            },
            {
              "process": "dwm.exe with pid 320"
            },
            {
              "type": "call",
              "pid": 6344,
              "cid": 1082
            },
            {
              "process": "svchost.exe with pid 404"
            },
            {
              "type": "call",
              "pid": 6344,
              "cid": 1083
            },
            {
              "process": "svchost.exe with pid 540"
            },
            {
              "type": "call",
              "pid": 6344,
              "cid": 1084
            },
            {
              "process": "svchost.exe with pid 396"
            },
            {
              "type": "call",
              "pid": 6344,
              "cid": 1085
            },
            {
              "process": "svchost.exe with pid 800"
            },
            {
              "type": "call",
              "pid": 6344,
              "cid": 1086
            },
            {
              "process": "svchost.exe with pid 1056"
            },
            {
              "type": "call",
              "pid": 6344,
              "cid": 1087
            },
            {
              "process": "svchost.exe with pid 1100"
            },
            {
              "type": "call",
              "pid": 6344,
              "cid": 1088
            },
            {
              "process": "svchost.exe with pid 1108"
            },
            {
              "type": "call",
              "pid": 6344,
              "cid": 1089
            },
            {
              "process": "svchost.exe with pid 1140"
            },
            {
              "type": "call",
              "pid": 6344,
              "cid": 1090
            },
            {
              "process": "svchost.exe with pid 1164"
            },
            {
              "type": "call",
              "pid": 6344,
              "cid": 1091
            },
            {
              "process": "svchost.exe with pid 1196"
            },
            {
              "type": "call",
              "pid": 6344,
              "cid": 1092
            },
            {
              "process": "svchost.exe with pid 1264"
            },
            {
              "type": "call",
              "pid": 6344,
              "cid": 1093
            },
            {
              "process": "svchost.exe with pid 1360"
            },
            {
              "type": "call",
              "pid": 6344,
              "cid": 1094
            },
            {
              "process": "svchost.exe with pid 1432"
            },
            {
              "type": "call",
              "pid": 6344,
              "cid": 1095
            },
            {
              "process": "svchost.exe with pid 1444"
            },
            {
              "type": "call",
              "pid": 6344,
              "cid": 1096
            },
            {
              "process": "svchost.exe with pid 1464"
            },
            {
              "type": "call",
              "pid": 6344,
              "cid": 1097
            },
            {
              "process": "svchost.exe with pid 1528"
            },
            {
              "type": "call",
              "pid": 6344,
              "cid": 1098
            },
            {
              "process": "Memory Compression with pid 1572"
            },
            {
              "type": "call",
              "pid": 6344,
              "cid": 1099
            },
            {
              "process": "svchost.exe with pid 1588"
            },
            {
              "type": "call",
              "pid": 6344,
              "cid": 1100
            },
            {
              "process": "svchost.exe with pid 1632"
            },
            {
              "type": "call",
              "pid": 6344,
              "cid": 1101
            },
            {
              "process": "svchost.exe with pid 1640"
            },
            {
              "type": "call",
              "pid": 6344,
              "cid": 1102
            },
            {
              "process": "svchost.exe with pid 1676"
            },
            {
              "type": "call",
              "pid": 6344,
              "cid": 1103
            },
            {
              "process": "svchost.exe with pid 1780"
            },
            {
              "type": "call",
              "pid": 6344,
              "cid": 1104
            },
            {
              "process": "svchost.exe with pid 1884"
            },
            {
              "type": "call",
              "pid": 6344,
              "cid": 1105
            },
            {
              "process": "svchost.exe with pid 1892"
            },
            {
              "type": "call",
              "pid": 6344,
              "cid": 1106
            },
            {
              "process": "svchost.exe with pid 1924"
            },
            {
              "type": "call",
              "pid": 6344,
              "cid": 1107
            },
            {
              "process": "svchost.exe with pid 1944"
            },
            {
              "type": "call",
              "pid": 6344,
              "cid": 1108
            },
            {
              "process": "svchost.exe with pid 1960"
            },
            {
              "type": "call",
              "pid": 6344,
              "cid": 1109
            },
            {
              "process": "svchost.exe with pid 2032"
            },
            {
              "type": "call",
              "pid": 6344,
              "cid": 1110
            },
            {
              "process": "svchost.exe with pid 2044"
            },
            {
              "type": "call",
              "pid": 6344,
              "cid": 1111
            },
            {
              "process": "spoolsv.exe with pid 2236"
            },
            {
              "type": "call",
              "pid": 6344,
              "cid": 1112
            },
            {
              "process": "svchost.exe with pid 2336"
            },
            {
              "type": "call",
              "pid": 6344,
              "cid": 1113
            },
            {
              "process": "svchost.exe with pid 2396"
            },
            {
              "type": "call",
              "pid": 6344,
              "cid": 1114
            },
            {
              "process": "svchost.exe with pid 2404"
            },
            {
              "type": "call",
              "pid": 6344,
              "cid": 1115
            },
            {
              "process": "svchost.exe with pid 2460"
            },
            {
              "type": "call",
              "pid": 6344,
              "cid": 1116
            },
            {
              "process": "svchost.exe with pid 2468"
            },
            {
              "type": "call",
              "pid": 6344,
              "cid": 1117
            },
            {
              "process": "svchost.exe with pid 2480"
            },
            {
              "type": "call",
              "pid": 6344,
              "cid": 1118
            },
            {
              "process": "svchost.exe with pid 2496"
            },
            {
              "type": "call",
              "pid": 6344,
              "cid": 1119
            },
            {
              "process": "svchost.exe with pid 2616"
            },
            {
              "type": "call",
              "pid": 6344,
              "cid": 1120
            },
            {
              "process": "svchost.exe with pid 2648"
            },
            {
              "type": "call",
              "pid": 6344,
              "cid": 1121
            },
            {
              "process": "MsMpEng.exe with pid 2672"
            },
            {
              "type": "call",
              "pid": 6344,
              "cid": 1122
            },
            {
              "process": "svchost.exe with pid 2680"
            },
            {
              "type": "call",
              "pid": 6344,
              "cid": 1123
            },
            {
              "process": "svchost.exe with pid 2720"
            },
            {
              "type": "call",
              "pid": 6344,
              "cid": 1124
            },
            {
              "process": "svchost.exe with pid 760"
            },
            {
              "type": "call",
              "pid": 6344,
              "cid": 1125
            },
            {
              "process": "svchost.exe with pid 3088"
            },
            {
              "type": "call",
              "pid": 6344,
              "cid": 1126
            },
            {
              "process": "NisSrv.exe with pid 3380"
            },
            {
              "type": "call",
              "pid": 6344,
              "cid": 1127
            },
            {
              "process": "svchost.exe with pid 3568"
            },
            {
              "type": "call",
              "pid": 6344,
              "cid": 1128
            },
            {
              "process": "svchost.exe with pid 3608"
            },
            {
              "type": "call",
              "pid": 6344,
              "cid": 1129
            },
            {
              "process": "svchost.exe with pid 3640"
            },
            {
              "type": "call",
              "pid": 6344,
              "cid": 1130
            },
            {
              "process": "svchost.exe with pid 3648"
            },
            {
              "type": "call",
              "pid": 6344,
              "cid": 1131
            },
            {
              "process": "sihost.exe with pid 3784"
            },
            {
              "type": "call",
              "pid": 6344,
              "cid": 1132
            },
            {
              "process": "svchost.exe with pid 3820"
            },
            {
              "type": "call",
              "pid": 6344,
              "cid": 1133
            },
            {
              "process": "svchost.exe with pid 3868"
            },
            {
              "type": "call",
              "pid": 6344,
              "cid": 1134
            },
            {
              "process": "MicrosoftEdgeUpdate.exe with pid 3936"
            },
            {
              "type": "call",
              "pid": 6344,
              "cid": 1135
            },
            {
              "process": "taskhostw.exe with pid 3972"
            },
            {
              "type": "call",
              "pid": 6344,
              "cid": 1136
            },
            {
              "process": "svchost.exe with pid 1008"
            },
            {
              "type": "call",
              "pid": 6344,
              "cid": 1137
            },
            {
              "process": "pyw.exe with pid 3256"
            },
            {
              "type": "call",
              "pid": 6344,
              "cid": 1138
            },
            {
              "process": "ctfmon.exe with pid 3244"
            },
            {
              "type": "call",
              "pid": 6344,
              "cid": 1139
            },
            {
              "process": "svchost.exe with pid 3544"
            },
            {
              "type": "call",
              "pid": 6344,
              "cid": 1140
            },
            {
              "process": "explorer.exe with pid 3176"
            },
            {
              "type": "call",
              "pid": 6344,
              "cid": 1141
            },
            {
              "process": "SearchIndexer.exe with pid 4112"
            },
            {
              "type": "call",
              "pid": 6344,
              "cid": 1142
            },
            {
              "process": "svchost.exe with pid 4284"
            },
            {
              "type": "call",
              "pid": 6344,
              "cid": 1143
            },
            {
              "process": "svchost.exe with pid 4364"
            },
            {
              "type": "call",
              "pid": 6344,
              "cid": 1144
            },
            {
              "process": "svchost.exe with pid 4436"
            },
            {
              "type": "call",
              "pid": 6344,
              "cid": 1145
            },
            {
              "process": "StartMenuExperienceHost.exe with pid 4932"
            },
            {
              "type": "call",
              "pid": 6344,
              "cid": 1146
            },
            {
              "process": "RuntimeBroker.exe with pid 5092"
            },
            {
              "type": "call",
              "pid": 6344,
              "cid": 1147
            },
            {
              "process": "pythonw.exe with pid 5100"
            },
            {
              "type": "call",
              "pid": 6344,
              "cid": 1148
            },
            {
              "process": "SearchApp.exe with pid 4760"
            },
            {
              "type": "call",
              "pid": 6344,
              "cid": 1149
            },
            {
              "process": "RuntimeBroker.exe with pid 5240"
            },
            {
              "type": "call",
              "pid": 6344,
              "cid": 1150
            },
            {
              "process": "svchost.exe with pid 5300"
            },
            {
              "type": "call",
              "pid": 6344,
              "cid": 1151
            },
            {
              "process": "dllhost.exe with pid 5416"
            },
            {
              "type": "call",
              "pid": 6344,
              "cid": 1152
            },
            {
              "process": "SettingSyncHost.exe with pid 5684"
            },
            {
              "type": "call",
              "pid": 6344,
              "cid": 1153
            },
            {
              "process": "LockApp.exe with pid 5856"
            },
            {
              "type": "call",
              "pid": 6344,
              "cid": 1154
            },
            {
              "process": "RuntimeBroker.exe with pid 5932"
            },
            {
              "type": "call",
              "pid": 6344,
              "cid": 1155
            },
            {
              "process": "RuntimeBroker.exe with pid 6020"
            },
            {
              "type": "call",
              "pid": 6344,
              "cid": 1156
            },
            {
              "process": "svchost.exe with pid 6104"
            },
            {
              "type": "call",
              "pid": 6344,
              "cid": 1157
            },
            {
              "process": "smartscreen.exe with pid 6280"
            },
            {
              "type": "call",
              "pid": 6344,
              "cid": 1158
            },
            {
              "process": "SecurityHealthSystray.exe with pid 6328"
            },
            {
              "type": "call",
              "pid": 6344,
              "cid": 1159
            },
            {
              "process": "SecurityHealthService.exe with pid 6356"
            },
            {
              "type": "call",
              "pid": 6344,
              "cid": 1160
            },
            {
              "process": "msedge.exe with pid 6424"
            },
            {
              "type": "call",
              "pid": 6344,
              "cid": 1161
            },
            {
              "process": "OneDrive.exe with pid 6444"
            },
            {
              "type": "call",
              "pid": 6344,
              "cid": 1162
            },
            {
              "process": "msedge.exe with pid 6528"
            },
            {
              "type": "call",
              "pid": 6344,
              "cid": 1163
            },
            {
              "process": "TextInputHost.exe with pid 6592"
            },
            {
              "type": "call",
              "pid": 6344,
              "cid": 1164
            },
            {
              "process": "msedge.exe with pid 6800"
            },
            {
              "type": "call",
              "pid": 6344,
              "cid": 1165
            },
            {
              "process": "msedge.exe with pid 6808"
            },
            {
              "type": "call",
              "pid": 6344,
              "cid": 1166
            },
            {
              "process": "msedge.exe with pid 6824"
            },
            {
              "type": "call",
              "pid": 6344,
              "cid": 1167
            },
            {
              "process": "svchost.exe with pid 7060"
            },
            {
              "type": "call",
              "pid": 6344,
              "cid": 1168
            },
            {
              "process": "dllhost.exe with pid 5564"
            },
            {
              "type": "call",
              "pid": 6344,
              "cid": 1169
            },
            {
              "process": "svchost.exe with pid 552"
            },
            {
              "type": "call",
              "pid": 6344,
              "cid": 1170
            },
            {
              "process": "msedge.exe with pid 3232"
            },
            {
              "type": "call",
              "pid": 6344,
              "cid": 1171
            },
            {
              "process": "msedge.exe with pid 7332"
            },
            {
              "type": "call",
              "pid": 6344,
              "cid": 1172
            },
            {
              "process": "svchost.exe with pid 7492"
            },
            {
              "type": "call",
              "pid": 6344,
              "cid": 1173
            },
            {
              "process": "svchost.exe with pid 7564"
            },
            {
              "type": "call",
              "pid": 6344,
              "cid": 1174
            },
            {
              "process": "ApplicationFrameHost.exe with pid 8116"
            },
            {
              "type": "call",
              "pid": 6344,
              "cid": 1175
            },
            {
              "process": "WinStore.App.exe with pid 8140"
            },
            {
              "type": "call",
              "pid": 6344,
              "cid": 1176
            },
            {
              "process": "RuntimeBroker.exe with pid 7396"
            },
            {
              "type": "call",
              "pid": 6344,
              "cid": 1177
            },
            {
              "process": "svchost.exe with pid 828"
            },
            {
              "type": "call",
              "pid": 6344,
              "cid": 1178
            },
            {
              "process": "audiodg.exe with pid 3476"
            },
            {
              "type": "call",
              "pid": 6344,
              "cid": 1179
            },
            {
              "process": "SkypeApp.exe with pid 532"
            },
            {
              "type": "call",
              "pid": 6344,
              "cid": 1180
            },
            {
              "process": "RuntimeBroker.exe with pid 1352"
            },
            {
              "type": "call",
              "pid": 6344,
              "cid": 1181
            },
            {
              "process": "SkypeBackgroundHost.exe with pid 2748"
            },
            {
              "type": "call",
              "pid": 6344,
              "cid": 1182
            },
            {
              "process": "svchost.exe with pid 3796"
            },
            {
              "type": "call",
              "pid": 6344,
              "cid": 1183
            },
            {
              "process": "svchost.exe with pid 4040"
            },
            {
              "type": "call",
              "pid": 6344,
              "cid": 1184
            },
            {
              "process": "svchost.exe with pid 8072"
            },
            {
              "type": "call",
              "pid": 6344,
              "cid": 1185
            },
            {
              "process": "svchost.exe with pid 5272"
            },
            {
              "type": "call",
              "pid": 6344,
              "cid": 1186
            },
            {
              "process": "svchost.exe with pid 7624"
            },
            {
              "type": "call",
              "pid": 6344,
              "cid": 1187
            },
            {
              "process": "SgrmBroker.exe with pid 6292"
            },
            {
              "type": "call",
              "pid": 6344,
              "cid": 1188
            },
            {
              "process": "svchost.exe with pid 388"
            },
            {
              "type": "call",
              "pid": 6344,
              "cid": 1189
            },
            {
              "process": "MoUsoCoreWorker.exe with pid 8092"
            },
            {
              "type": "call",
              "pid": 6344,
              "cid": 1190
            },
            {
              "process": "svchost.exe with pid 1452"
            },
            {
              "type": "call",
              "pid": 6344,
              "cid": 1191
            },
            {
              "process": "svchost.exe with pid 2068"
            },
            {
              "type": "call",
              "pid": 6344,
              "cid": 1192
            },
            {
              "process": "svchost.exe with pid 8508"
            },
            {
              "type": "call",
              "pid": 6344,
              "cid": 1193
            },
            {
              "process": "svchost.exe with pid 8516"
            },
            {
              "type": "call",
              "pid": 6344,
              "cid": 1194
            },
            {
              "process": "svchost.exe with pid 8568"
            },
            {
              "type": "call",
              "pid": 6344,
              "cid": 1195
            },
            {
              "process": "svchost.exe with pid 8636"
            },
            {
              "type": "call",
              "pid": 6344,
              "cid": 1196
            },
            {
              "process": "dasHost.exe with pid 8672"
            },
            {
              "type": "call",
              "pid": 6344,
              "cid": 1197
            },
            {
              "process": "upfc.exe with pid 1492"
            },
            {
              "type": "call",
              "pid": 6344,
              "cid": 1198
            },
            {
              "process": "CompatTelRunner.exe with pid 8928"
            },
            {
              "type": "call",
              "pid": 6344,
              "cid": 1199
            },
            {
              "process": "OneDriveStandaloneUpdater.exe with pid 1404"
            },
            {
              "type": "call",
              "pid": 6344,
              "cid": 1200
            },
            {
              "process": "OneDriveStandaloneUpdater.exe with pid 1272"
            },
            {
              "type": "call",
              "pid": 6344,
              "cid": 1201
            },
            {
              "process": "conhost.exe with pid 7880"
            },
            {
              "type": "call",
              "pid": 6344,
              "cid": 1202
            },
            {
              "process": "svchost.exe with pid 976"
            },
            {
              "type": "call",
              "pid": 6344,
              "cid": 1203
            },
            {
              "process": "rovwer.exe with pid 1224"
            },
            {
              "type": "call",
              "pid": 6344,
              "cid": 1204
            },
            {
              "process": "svchost.exe with pid 7996"
            },
            {
              "type": "call",
              "pid": 6344,
              "cid": 1205
            },
            {
              "process": "svchost.exe with pid 7776"
            },
            {
              "type": "call",
              "pid": 6344,
              "cid": 1206
            },
            {
              "process": "MicrosoftEdgeUpdate.exe with pid 6344"
            },
            {
              "type": "call",
              "pid": 6344,
              "cid": 1207
            }
          ],
          "new_data": [],
          "alert": false,
          "families": []
        },
        {
          "name": "process_interest",
          "description": "Expresses interest in specific running processes",
          "categories": [
            "generic"
          ],
          "severity": 2,
          "weight": 1,
          "confidence": 100,
          "references": [],
          "data": [
            {
              "type": "call",
              "pid": 6344,
              "cid": 1068
            },
            {
              "type": "call",
              "pid": 6344,
              "cid": 1069
            },
            {
              "type": "call",
              "pid": 6344,
              "cid": 1070
            },
            {
              "type": "call",
              "pid": 6344,
              "cid": 1071
            },
            {
              "type": "call",
              "pid": 6344,
              "cid": 1072
            },
            {
              "type": "call",
              "pid": 6344,
              "cid": 1073
            },
            {
              "type": "call",
              "pid": 6344,
              "cid": 1074
            },
            {
              "type": "call",
              "pid": 6344,
              "cid": 1075
            },
            {
              "type": "call",
              "pid": 6344,
              "cid": 1076
            },
            {
              "type": "call",
              "pid": 6344,
              "cid": 1077
            },
            {
              "type": "call",
              "pid": 6344,
              "cid": 1078
            },
            {
              "type": "call",
              "pid": 6344,
              "cid": 1079
            },
            {
              "type": "call",
              "pid": 6344,
              "cid": 1080
            },
            {
              "type": "call",
              "pid": 6344,
              "cid": 1081
            },
            {
              "type": "call",
              "pid": 6344,
              "cid": 1082
            },
            {
              "type": "call",
              "pid": 6344,
              "cid": 1083
            },
            {
              "type": "call",
              "pid": 6344,
              "cid": 1084
            },
            {
              "type": "call",
              "pid": 6344,
              "cid": 1085
            },
            {
              "type": "call",
              "pid": 6344,
              "cid": 1086
            },
            {
              "type": "call",
              "pid": 6344,
              "cid": 1087
            },
            {
              "type": "call",
              "pid": 6344,
              "cid": 1088
            },
            {
              "type": "call",
              "pid": 6344,
              "cid": 1089
            },
            {
              "type": "call",
              "pid": 6344,
              "cid": 1090
            },
            {
              "type": "call",
              "pid": 6344,
              "cid": 1091
            },
            {
              "type": "call",
              "pid": 6344,
              "cid": 1092
            },
            {
              "type": "call",
              "pid": 6344,
              "cid": 1093
            },
            {
              "type": "call",
              "pid": 6344,
              "cid": 1094
            },
            {
              "type": "call",
              "pid": 6344,
              "cid": 1095
            },
            {
              "type": "call",
              "pid": 6344,
              "cid": 1096
            },
            {
              "type": "call",
              "pid": 6344,
              "cid": 1097
            },
            {
              "type": "call",
              "pid": 6344,
              "cid": 1098
            },
            {
              "type": "call",
              "pid": 6344,
              "cid": 1099
            },
            {
              "type": "call",
              "pid": 6344,
              "cid": 1100
            },
            {
              "type": "call",
              "pid": 6344,
              "cid": 1101
            },
            {
              "type": "call",
              "pid": 6344,
              "cid": 1102
            },
            {
              "type": "call",
              "pid": 6344,
              "cid": 1103
            },
            {
              "type": "call",
              "pid": 6344,
              "cid": 1104
            },
            {
              "type": "call",
              "pid": 6344,
              "cid": 1105
            },
            {
              "type": "call",
              "pid": 6344,
              "cid": 1106
            },
            {
              "type": "call",
              "pid": 6344,
              "cid": 1107
            },
            {
              "type": "call",
              "pid": 6344,
              "cid": 1108
            },
            {
              "type": "call",
              "pid": 6344,
              "cid": 1109
            },
            {
              "type": "call",
              "pid": 6344,
              "cid": 1110
            },
            {
              "type": "call",
              "pid": 6344,
              "cid": 1111
            },
            {
              "type": "call",
              "pid": 6344,
              "cid": 1112
            },
            {
              "type": "call",
              "pid": 6344,
              "cid": 1113
            },
            {
              "type": "call",
              "pid": 6344,
              "cid": 1114
            },
            {
              "type": "call",
              "pid": 6344,
              "cid": 1115
            },
            {
              "type": "call",
              "pid": 6344,
              "cid": 1116
            },
            {
              "type": "call",
              "pid": 6344,
              "cid": 1117
            },
            {
              "type": "call",
              "pid": 6344,
              "cid": 1118
            },
            {
              "type": "call",
              "pid": 6344,
              "cid": 1119
            },
            {
              "type": "call",
              "pid": 6344,
              "cid": 1120
            },
            {
              "type": "call",
              "pid": 6344,
              "cid": 1121
            },
            {
              "type": "call",
              "pid": 6344,
              "cid": 1122
            },
            {
              "type": "call",
              "pid": 6344,
              "cid": 1123
            },
            {
              "type": "call",
              "pid": 6344,
              "cid": 1124
            },
            {
              "type": "call",
              "pid": 6344,
              "cid": 1125
            },
            {
              "type": "call",
              "pid": 6344,
              "cid": 1126
            },
            {
              "type": "call",
              "pid": 6344,
              "cid": 1127
            },
            {
              "type": "call",
              "pid": 6344,
              "cid": 1128
            },
            {
              "type": "call",
              "pid": 6344,
              "cid": 1129
            },
            {
              "type": "call",
              "pid": 6344,
              "cid": 1130
            },
            {
              "type": "call",
              "pid": 6344,
              "cid": 1131
            },
            {
              "type": "call",
              "pid": 6344,
              "cid": 1132
            },
            {
              "type": "call",
              "pid": 6344,
              "cid": 1133
            },
            {
              "type": "call",
              "pid": 6344,
              "cid": 1134
            },
            {
              "type": "call",
              "pid": 6344,
              "cid": 1135
            },
            {
              "type": "call",
              "pid": 6344,
              "cid": 1136
            },
            {
              "type": "call",
              "pid": 6344,
              "cid": 1137
            },
            {
              "type": "call",
              "pid": 6344,
              "cid": 1138
            },
            {
              "type": "call",
              "pid": 6344,
              "cid": 1139
            },
            {
              "type": "call",
              "pid": 6344,
              "cid": 1140
            },
            {
              "type": "call",
              "pid": 6344,
              "cid": 1141
            },
            {
              "type": "call",
              "pid": 6344,
              "cid": 1142
            },
            {
              "type": "call",
              "pid": 6344,
              "cid": 1143
            },
            {
              "type": "call",
              "pid": 6344,
              "cid": 1144
            },
            {
              "type": "call",
              "pid": 6344,
              "cid": 1145
            },
            {
              "type": "call",
              "pid": 6344,
              "cid": 1146
            },
            {
              "type": "call",
              "pid": 6344,
              "cid": 1147
            },
            {
              "type": "call",
              "pid": 6344,
              "cid": 1148
            },
            {
              "type": "call",
              "pid": 6344,
              "cid": 1149
            },
            {
              "type": "call",
              "pid": 6344,
              "cid": 1150
            },
            {
              "type": "call",
              "pid": 6344,
              "cid": 1151
            },
            {
              "type": "call",
              "pid": 6344,
              "cid": 1152
            },
            {
              "type": "call",
              "pid": 6344,
              "cid": 1153
            },
            {
              "type": "call",
              "pid": 6344,
              "cid": 1154
            },
            {
              "type": "call",
              "pid": 6344,
              "cid": 1155
            },
            {
              "type": "call",
              "pid": 6344,
              "cid": 1156
            },
            {
              "type": "call",
              "pid": 6344,
              "cid": 1157
            },
            {
              "type": "call",
              "pid": 6344,
              "cid": 1158
            },
            {
              "type": "call",
              "pid": 6344,
              "cid": 1159
            },
            {
              "type": "call",
              "pid": 6344,
              "cid": 1160
            },
            {
              "type": "call",
              "pid": 6344,
              "cid": 1161
            },
            {
              "type": "call",
              "pid": 6344,
              "cid": 1162
            },
            {
              "type": "call",
              "pid": 6344,
              "cid": 1163
            },
            {
              "type": "call",
              "pid": 6344,
              "cid": 1164
            },
            {
              "type": "call",
              "pid": 6344,
              "cid": 1165
            },
            {
              "type": "call",
              "pid": 6344,
              "cid": 1166
            },
            {
              "type": "call",
              "pid": 6344,
              "cid": 1167
            },
            {
              "type": "call",
              "pid": 6344,
              "cid": 1168
            },
            {
              "type": "call",
              "pid": 6344,
              "cid": 1169
            },
            {
              "type": "call",
              "pid": 6344,
              "cid": 1170
            },
            {
              "type": "call",
              "pid": 6344,
              "cid": 1171
            },
            {
              "type": "call",
              "pid": 6344,
              "cid": 1172
            },
            {
              "type": "call",
              "pid": 6344,
              "cid": 1173
            },
            {
              "type": "call",
              "pid": 6344,
              "cid": 1174
            },
            {
              "type": "call",
              "pid": 6344,
              "cid": 1175
            },
            {
              "type": "call",
              "pid": 6344,
              "cid": 1176
            },
            {
              "type": "call",
              "pid": 6344,
              "cid": 1177
            },
            {
              "type": "call",
              "pid": 6344,
              "cid": 1178
            },
            {
              "type": "call",
              "pid": 6344,
              "cid": 1179
            },
            {
              "type": "call",
              "pid": 6344,
              "cid": 1180
            },
            {
              "type": "call",
              "pid": 6344,
              "cid": 1181
            },
            {
              "type": "call",
              "pid": 6344,
              "cid": 1182
            },
            {
              "type": "call",
              "pid": 6344,
              "cid": 1183
            },
            {
              "type": "call",
              "pid": 6344,
              "cid": 1184
            },
            {
              "type": "call",
              "pid": 6344,
              "cid": 1185
            },
            {
              "type": "call",
              "pid": 6344,
              "cid": 1186
            },
            {
              "type": "call",
              "pid": 6344,
              "cid": 1187
            },
            {
              "type": "call",
              "pid": 6344,
              "cid": 1188
            },
            {
              "type": "call",
              "pid": 6344,
              "cid": 1189
            },
            {
              "type": "call",
              "pid": 6344,
              "cid": 1190
            },
            {
              "type": "call",
              "pid": 6344,
              "cid": 1191
            },
            {
              "type": "call",
              "pid": 6344,
              "cid": 1192
            },
            {
              "type": "call",
              "pid": 6344,
              "cid": 1193
            },
            {
              "type": "call",
              "pid": 6344,
              "cid": 1194
            },
            {
              "type": "call",
              "pid": 6344,
              "cid": 1195
            },
            {
              "type": "call",
              "pid": 6344,
              "cid": 1196
            },
            {
              "type": "call",
              "pid": 6344,
              "cid": 1197
            },
            {
              "type": "call",
              "pid": 6344,
              "cid": 1198
            },
            {
              "type": "call",
              "pid": 6344,
              "cid": 1199
            },
            {
              "type": "call",
              "pid": 6344,
              "cid": 1200
            },
            {
              "type": "call",
              "pid": 6344,
              "cid": 1201
            },
            {
              "type": "call",
              "pid": 6344,
              "cid": 1202
            },
            {
              "type": "call",
              "pid": 6344,
              "cid": 1203
            },
            {
              "type": "call",
              "pid": 6344,
              "cid": 1204
            },
            {
              "type": "call",
              "pid": 6344,
              "cid": 1205
            },
            {
              "type": "call",
              "pid": 6344,
              "cid": 1206
            },
            {
              "type": "call",
              "pid": 6344,
              "cid": 1207
            },
            {
              "process": "MicrosoftEdgeUpdate.exe"
            }
          ],
          "new_data": [],
          "alert": false,
          "families": []
        },
        {
          "name": "antisandbox_unhook",
          "description": "Tries to unhook or modify Windows functions monitored by CAPE",
          "categories": [
            "anti-sandbox"
          ],
          "severity": 3,
          "weight": 1,
          "confidence": 60,
          "references": [],
          "data": [
            {
              "type": "call",
              "pid": 6344,
              "cid": 1239
            },
            {
              "type": "call",
              "pid": 6344,
              "cid": 1240
            },
            {
              "type": "call",
              "pid": 6344,
              "cid": 1241
            },
            {
              "type": "call",
              "pid": 6344,
              "cid": 1242
            },
            {
              "type": "call",
              "pid": 6344,
              "cid": 1243
            },
            {
              "type": "call",
              "pid": 6344,
              "cid": 1244
            },
            {
              "type": "call",
              "pid": 6344,
              "cid": 1245
            },
            {
              "type": "call",
              "pid": 6344,
              "cid": 1246
            },
            {
              "type": "call",
              "pid": 6344,
              "cid": 1247
            },
            {
              "type": "call",
              "pid": 6344,
              "cid": 1248
            },
            {
              "type": "call",
              "pid": 6344,
              "cid": 1249
            },
            {
              "type": "call",
              "pid": 6344,
              "cid": 1250
            },
            {
              "type": "call",
              "pid": 6344,
              "cid": 1251
            },
            {
              "type": "call",
              "pid": 6344,
              "cid": 1252
            },
            {
              "unhook": "function_name: CryptHashData, type: removal"
            },
            {
              "unhook": "function_name: CryptCreateHash, type: removal"
            },
            {
              "unhook": "function_name: CryptAcquireContextA, type: removal"
            },
            {
              "unhook": "function_name: CryptEncrypt, type: removal"
            },
            {
              "unhook": "function_name: CryptHashSessionKey, type: removal"
            },
            {
              "unhook": "function_name: CryptAcquireContextW, type: removal"
            },
            {
              "unhook": "function_name: CryptDecrypt, type: removal"
            },
            {
              "unhook": "function_name: CryptEnumProvidersW, type: removal"
            },
            {
              "unhook": "function_name: VarBstrCat, type: removal"
            },
            {
              "unhook": "function_name: CryptImportKey, type: removal"
            },
            {
              "unhook": "function_name: CryptExportKey, type: removal"
            },
            {
              "unhook": "function_name: CryptGenKey, type: removal"
            },
            {
              "unhook": "function_name: CryptEnumProvidersA, type: removal"
            },
            {
              "unhook": "function_name: CryptGenRandom, type: removal"
            }
          ],
          "new_data": [],
          "alert": false,
          "families": []
        }
      ],
      "failure_reason": null,
      "improvement_suggestions": [],
      "debugger_log": null,
      "raw_response": "## Step 1: Identify suspicious instructions and extract them\n\n- Conditional jumps (JE, JNE, JZ, JNZ, etc.)\n- Test/compare instructions (TEST, CMP)\n- Function calls (CALL)\n\n**Suspicious Instructions:**\n\n* JE at address 0041B90E\n* TEST AL, 01h at address 0041B91C\n* CALL dword ptr [0042F13Ch] at address 0041B923\n* CALL dword ptr [0042F140h] at address 0041B92A\n\n**Step 2: Trace the exit path backwards to understand evasion**\n\nStarting from the exit (0041B93C), trace backwards:\n\n- The instruction that directly causes the exit is `FF15A0F14200` at address 0041B93C.\n- The conditional jump leading to this path is not directly related, but it seems like a loop or repetition because of similar code in both traces.\n- The check determining the jump's direction is unclear without more information.\n\n**Step 3: Select different bypass candidates**\n\nChoose 3 DIFFERENT instructions that could potentially be used for evasion:\n\n1. `JE` at address 0041B90E\n2. `TEST AL, 01h` at address 0041B91C\n3. `CALL dword ptr [0042F13Ch]` at address 0041B923\n\n**Step 4: Build patterns (6-20 bytes each)**\n\nCombine each candidate with adjacent instructions to create a specific pattern:\n\n1. **Pattern 1:** Combine JE, TEST, and CALL instructions\n```\n74 20 85 C0 0F 84 ?? ?? ?? ?? E8 F7 25 00 00\n```\n\n2. **Pattern 2:** Combine TEST AL, 01h with MOV EAX instruction\n```\nA8 01 8B 45 ?? FF 15 A0 F1 42 00\n```\n\n3. **Pattern 3:** Combine CALL dword ptr [0042F13Ch] with PUSH EAX and POP ECX instructions\n```\nFF 15 CF 14 20 00 50 FF 35 C0 F1 42 00\n```\n\n**Step 5: Apply wildcards and generate the YARA rule**\n\nReplace address/offset bytes with `??`:\n\n```yara\nrule Bypass_Sample\n{\n    meta:\n        description = \"Evasion bypass rule\"\n        cape_options = \"bp0=$pattern0+0,action0=skip,bp1=$pattern1+0,action1=skip,bp2=$pattern2+0,action2=skip,count=0\"\n\n    strings:\n        $pattern0 = { [6-20 bytes with wildcards] 74 20 85 C0 0F 84 ?? ?? ?? ?? E8 F7 25 00 00 }\n        $pattern1 = { [6-20 bytes - DIFFERENT sequence] A8 01 8B 45 ?? FF 15 A0 F1 42 00 }\n        $pattern2 = { [6-20 bytes - DIFFERENT sequence] FF 15 CF 14 20 00 50 FF 35 C0 F1 42 00 }\n\n    condition:\n        any of them\n}\n```",
      "yara_file": "ablation_results\\llama3.1_8b\\Iter\\Iter\\8cd1795a98c9fc8a\\iter0_v1.yar"
    }
  ],
  "best_attempt": {
    "iteration": 0,
    "prompt_version": "v1",
    "yara_rule": "rule Bypass_Sample\n{\n    meta:\n        description = \"Evasion bypass rule\"\n        cape_options = \"bp0=$pattern0+0,action0=skip,bp1=$pattern1+0,action1=skip,bp2=$pattern2+0,action2=skip,count=0\"\n\n    strings:\n        $pattern0 = { 20 74 20 85 C0 0F 84 ?? ?? ?? ?? E8 F7 25 00 00 }\n        $pattern1 = { 20 FF EE CE A8 01 8B 45 ?? FF 15 A0 F1 42 00 }\n        $pattern2 = { 20 FF EE CE FF 15 CF 14 20 00 50 FF 35 C0 F1 42 00 }\n\n    condition:\n        any of them\n}",
    "pattern_type": "UNKNOWN",
    "confidence": 50,
    "opcodes": "",
    "task_id": "1948",
    "status": "bypass_success",
    "rule_hit": true,
    "baseline_signatures": 26,
    "new_signatures": 4,
    "new_signature_names": [
      "process_interest",
      "antisandbox_unhook",
      "reads_memory_remote_process",
      "enumerates_running_processes"
    ],
    "new_signature_details": [
      {
        "name": "reads_memory_remote_process",
        "description": "Reads from the memory of another process",
        "categories": [
          "memory scraping",
          "injection"
        ],
        "severity": 2,
        "weight": 1,
        "confidence": 100,
        "references": [],
        "data": [
          {
            "read_memory": "Process microsoftedgeupdate.exe with process ID 6344 read from the memory of process handle 0x00000354"
          },
          {
            "type": "call",
            "pid": 6344,
            "cid": 1642
          },
          {
            "type": "call",
            "pid": 6344,
            "cid": 1643
          },
          {
            "type": "call",
            "pid": 6344,
            "cid": 1644
          }
        ],
        "new_data": [],
        "alert": false,
        "families": []
      },
      {
        "name": "enumerates_running_processes",
        "description": "Enumerates running processes",
        "categories": [
          "discovery"
        ],
        "severity": 2,
        "weight": 1,
        "confidence": 100,
        "references": [],
        "data": [
          {
            "process": "System with pid 4"
          },
          {
            "type": "call",
            "pid": 6344,
            "cid": 1068
          },
          {
            "process": "Registry with pid 92"
          },
          {
            "type": "call",
            "pid": 6344,
            "cid": 1069
          },
          {
            "process": "smss.exe with pid 336"
          },
          {
            "type": "call",
            "pid": 6344,
            "cid": 1070
          },
          {
            "process": "csrss.exe with pid 448"
          },
          {
            "type": "call",
            "pid": 6344,
            "cid": 1071
          },
          {
            "process": "wininit.exe with pid 524"
          },
          {
            "type": "call",
            "pid": 6344,
            "cid": 1072
          },
          {
            "process": "csrss.exe with pid 536"
          },
          {
            "type": "call",
            "pid": 6344,
            "cid": 1073
          },
          {
            "process": "winlogon.exe with pid 616"
          },
          {
            "type": "call",
            "pid": 6344,
            "cid": 1074
          },
          {
            "process": "services.exe with pid 656"
          },
          {
            "type": "call",
            "pid": 6344,
            "cid": 1075
          },
          {
            "process": "lsass.exe with pid 680"
          },
          {
            "type": "call",
            "pid": 6344,
            "cid": 1076
          },
          {
            "process": "svchost.exe with pid 776"
          },
          {
            "type": "call",
            "pid": 6344,
            "cid": 1077
          },
          {
            "process": "fontdrvhost.exe with pid 808"
          },
          {
            "type": "call",
            "pid": 6344,
            "cid": 1078
          },
          {
            "process": "fontdrvhost.exe with pid 816"
          },
          {
            "type": "call",
            "pid": 6344,
            "cid": 1079
          },
          {
            "process": "svchost.exe with pid 896"
          },
          {
            "type": "call",
            "pid": 6344,
            "cid": 1080
          },
          {
            "process": "svchost.exe with pid 956"
          },
          {
            "type": "call",
            "pid": 6344,
            "cid": 1081
          },
          {
            "process": "dwm.exe with pid 320"
          },
          {
            "type": "call",
            "pid": 6344,
            "cid": 1082
          },
          {
            "process": "svchost.exe with pid 404"
          },
          {
            "type": "call",
            "pid": 6344,
            "cid": 1083
          },
          {
            "process": "svchost.exe with pid 540"
          },
          {
            "type": "call",
            "pid": 6344,
            "cid": 1084
          },
          {
            "process": "svchost.exe with pid 396"
          },
          {
            "type": "call",
            "pid": 6344,
            "cid": 1085
          },
          {
            "process": "svchost.exe with pid 800"
          },
          {
            "type": "call",
            "pid": 6344,
            "cid": 1086
          },
          {
            "process": "svchost.exe with pid 1056"
          },
          {
            "type": "call",
            "pid": 6344,
            "cid": 1087
          },
          {
            "process": "svchost.exe with pid 1100"
          },
          {
            "type": "call",
            "pid": 6344,
            "cid": 1088
          },
          {
            "process": "svchost.exe with pid 1108"
          },
          {
            "type": "call",
            "pid": 6344,
            "cid": 1089
          },
          {
            "process": "svchost.exe with pid 1140"
          },
          {
            "type": "call",
            "pid": 6344,
            "cid": 1090
          },
          {
            "process": "svchost.exe with pid 1164"
          },
          {
            "type": "call",
            "pid": 6344,
            "cid": 1091
          },
          {
            "process": "svchost.exe with pid 1196"
          },
          {
            "type": "call",
            "pid": 6344,
            "cid": 1092
          },
          {
            "process": "svchost.exe with pid 1264"
          },
          {
            "type": "call",
            "pid": 6344,
            "cid": 1093
          },
          {
            "process": "svchost.exe with pid 1360"
          },
          {
            "type": "call",
            "pid": 6344,
            "cid": 1094
          },
          {
            "process": "svchost.exe with pid 1432"
          },
          {
            "type": "call",
            "pid": 6344,
            "cid": 1095
          },
          {
            "process": "svchost.exe with pid 1444"
          },
          {
            "type": "call",
            "pid": 6344,
            "cid": 1096
          },
          {
            "process": "svchost.exe with pid 1464"
          },
          {
            "type": "call",
            "pid": 6344,
            "cid": 1097
          },
          {
            "process": "svchost.exe with pid 1528"
          },
          {
            "type": "call",
            "pid": 6344,
            "cid": 1098
          },
          {
            "process": "Memory Compression with pid 1572"
          },
          {
            "type": "call",
            "pid": 6344,
            "cid": 1099
          },
          {
            "process": "svchost.exe with pid 1588"
          },
          {
            "type": "call",
            "pid": 6344,
            "cid": 1100
          },
          {
            "process": "svchost.exe with pid 1632"
          },
          {
            "type": "call",
            "pid": 6344,
            "cid": 1101
          },
          {
            "process": "svchost.exe with pid 1640"
          },
          {
            "type": "call",
            "pid": 6344,
            "cid": 1102
          },
          {
            "process": "svchost.exe with pid 1676"
          },
          {
            "type": "call",
            "pid": 6344,
            "cid": 1103
          },
          {
            "process": "svchost.exe with pid 1780"
          },
          {
            "type": "call",
            "pid": 6344,
            "cid": 1104
          },
          {
            "process": "svchost.exe with pid 1884"
          },
          {
            "type": "call",
            "pid": 6344,
            "cid": 1105
          },
          {
            "process": "svchost.exe with pid 1892"
          },
          {
            "type": "call",
            "pid": 6344,
            "cid": 1106
          },
          {
            "process": "svchost.exe with pid 1924"
          },
          {
            "type": "call",
            "pid": 6344,
            "cid": 1107
          },
          {
            "process": "svchost.exe with pid 1944"
          },
          {
            "type": "call",
            "pid": 6344,
            "cid": 1108
          },
          {
            "process": "svchost.exe with pid 1960"
          },
          {
            "type": "call",
            "pid": 6344,
            "cid": 1109
          },
          {
            "process": "svchost.exe with pid 2032"
          },
          {
            "type": "call",
            "pid": 6344,
            "cid": 1110
          },
          {
            "process": "svchost.exe with pid 2044"
          },
          {
            "type": "call",
            "pid": 6344,
            "cid": 1111
          },
          {
            "process": "spoolsv.exe with pid 2236"
          },
          {
            "type": "call",
            "pid": 6344,
            "cid": 1112
          },
          {
            "process": "svchost.exe with pid 2336"
          },
          {
            "type": "call",
            "pid": 6344,
            "cid": 1113
          },
          {
            "process": "svchost.exe with pid 2396"
          },
          {
            "type": "call",
            "pid": 6344,
            "cid": 1114
          },
          {
            "process": "svchost.exe with pid 2404"
          },
          {
            "type": "call",
            "pid": 6344,
            "cid": 1115
          },
          {
            "process": "svchost.exe with pid 2460"
          },
          {
            "type": "call",
            "pid": 6344,
            "cid": 1116
          },
          {
            "process": "svchost.exe with pid 2468"
          },
          {
            "type": "call",
            "pid": 6344,
            "cid": 1117
          },
          {
            "process": "svchost.exe with pid 2480"
          },
          {
            "type": "call",
            "pid": 6344,
            "cid": 1118
          },
          {
            "process": "svchost.exe with pid 2496"
          },
          {
            "type": "call",
            "pid": 6344,
            "cid": 1119
          },
          {
            "process": "svchost.exe with pid 2616"
          },
          {
            "type": "call",
            "pid": 6344,
            "cid": 1120
          },
          {
            "process": "svchost.exe with pid 2648"
          },
          {
            "type": "call",
            "pid": 6344,
            "cid": 1121
          },
          {
            "process": "MsMpEng.exe with pid 2672"
          },
          {
            "type": "call",
            "pid": 6344,
            "cid": 1122
          },
          {
            "process": "svchost.exe with pid 2680"
          },
          {
            "type": "call",
            "pid": 6344,
            "cid": 1123
          },
          {
            "process": "svchost.exe with pid 2720"
          },
          {
            "type": "call",
            "pid": 6344,
            "cid": 1124
          },
          {
            "process": "svchost.exe with pid 760"
          },
          {
            "type": "call",
            "pid": 6344,
            "cid": 1125
          },
          {
            "process": "svchost.exe with pid 3088"
          },
          {
            "type": "call",
            "pid": 6344,
            "cid": 1126
          },
          {
            "process": "NisSrv.exe with pid 3380"
          },
          {
            "type": "call",
            "pid": 6344,
            "cid": 1127
          },
          {
            "process": "svchost.exe with pid 3568"
          },
          {
            "type": "call",
            "pid": 6344,
            "cid": 1128
          },
          {
            "process": "svchost.exe with pid 3608"
          },
          {
            "type": "call",
            "pid": 6344,
            "cid": 1129
          },
          {
            "process": "svchost.exe with pid 3640"
          },
          {
            "type": "call",
            "pid": 6344,
            "cid": 1130
          },
          {
            "process": "svchost.exe with pid 3648"
          },
          {
            "type": "call",
            "pid": 6344,
            "cid": 1131
          },
          {
            "process": "sihost.exe with pid 3784"
          },
          {
            "type": "call",
            "pid": 6344,
            "cid": 1132
          },
          {
            "process": "svchost.exe with pid 3820"
          },
          {
            "type": "call",
            "pid": 6344,
            "cid": 1133
          },
          {
            "process": "svchost.exe with pid 3868"
          },
          {
            "type": "call",
            "pid": 6344,
            "cid": 1134
          },
          {
            "process": "MicrosoftEdgeUpdate.exe with pid 3936"
          },
          {
            "type": "call",
            "pid": 6344,
            "cid": 1135
          },
          {
            "process": "taskhostw.exe with pid 3972"
          },
          {
            "type": "call",
            "pid": 6344,
            "cid": 1136
          },
          {
            "process": "svchost.exe with pid 1008"
          },
          {
            "type": "call",
            "pid": 6344,
            "cid": 1137
          },
          {
            "process": "pyw.exe with pid 3256"
          },
          {
            "type": "call",
            "pid": 6344,
            "cid": 1138
          },
          {
            "process": "ctfmon.exe with pid 3244"
          },
          {
            "type": "call",
            "pid": 6344,
            "cid": 1139
          },
          {
            "process": "svchost.exe with pid 3544"
          },
          {
            "type": "call",
            "pid": 6344,
            "cid": 1140
          },
          {
            "process": "explorer.exe with pid 3176"
          },
          {
            "type": "call",
            "pid": 6344,
            "cid": 1141
          },
          {
            "process": "SearchIndexer.exe with pid 4112"
          },
          {
            "type": "call",
            "pid": 6344,
            "cid": 1142
          },
          {
            "process": "svchost.exe with pid 4284"
          },
          {
            "type": "call",
            "pid": 6344,
            "cid": 1143
          },
          {
            "process": "svchost.exe with pid 4364"
          },
          {
            "type": "call",
            "pid": 6344,
            "cid": 1144
          },
          {
            "process": "svchost.exe with pid 4436"
          },
          {
            "type": "call",
            "pid": 6344,
            "cid": 1145
          },
          {
            "process": "StartMenuExperienceHost.exe with pid 4932"
          },
          {
            "type": "call",
            "pid": 6344,
            "cid": 1146
          },
          {
            "process": "RuntimeBroker.exe with pid 5092"
          },
          {
            "type": "call",
            "pid": 6344,
            "cid": 1147
          },
          {
            "process": "pythonw.exe with pid 5100"
          },
          {
            "type": "call",
            "pid": 6344,
            "cid": 1148
          },
          {
            "process": "SearchApp.exe with pid 4760"
          },
          {
            "type": "call",
            "pid": 6344,
            "cid": 1149
          },
          {
            "process": "RuntimeBroker.exe with pid 5240"
          },
          {
            "type": "call",
            "pid": 6344,
            "cid": 1150
          },
          {
            "process": "svchost.exe with pid 5300"
          },
          {
            "type": "call",
            "pid": 6344,
            "cid": 1151
          },
          {
            "process": "dllhost.exe with pid 5416"
          },
          {
            "type": "call",
            "pid": 6344,
            "cid": 1152
          },
          {
            "process": "SettingSyncHost.exe with pid 5684"
          },
          {
            "type": "call",
            "pid": 6344,
            "cid": 1153
          },
          {
            "process": "LockApp.exe with pid 5856"
          },
          {
            "type": "call",
            "pid": 6344,
            "cid": 1154
          },
          {
            "process": "RuntimeBroker.exe with pid 5932"
          },
          {
            "type": "call",
            "pid": 6344,
            "cid": 1155
          },
          {
            "process": "RuntimeBroker.exe with pid 6020"
          },
          {
            "type": "call",
            "pid": 6344,
            "cid": 1156
          },
          {
            "process": "svchost.exe with pid 6104"
          },
          {
            "type": "call",
            "pid": 6344,
            "cid": 1157
          },
          {
            "process": "smartscreen.exe with pid 6280"
          },
          {
            "type": "call",
            "pid": 6344,
            "cid": 1158
          },
          {
            "process": "SecurityHealthSystray.exe with pid 6328"
          },
          {
            "type": "call",
            "pid": 6344,
            "cid": 1159
          },
          {
            "process": "SecurityHealthService.exe with pid 6356"
          },
          {
            "type": "call",
            "pid": 6344,
            "cid": 1160
          },
          {
            "process": "msedge.exe with pid 6424"
          },
          {
            "type": "call",
            "pid": 6344,
            "cid": 1161
          },
          {
            "process": "OneDrive.exe with pid 6444"
          },
          {
            "type": "call",
            "pid": 6344,
            "cid": 1162
          },
          {
            "process": "msedge.exe with pid 6528"
          },
          {
            "type": "call",
            "pid": 6344,
            "cid": 1163
          },
          {
            "process": "TextInputHost.exe with pid 6592"
          },
          {
            "type": "call",
            "pid": 6344,
            "cid": 1164
          },
          {
            "process": "msedge.exe with pid 6800"
          },
          {
            "type": "call",
            "pid": 6344,
            "cid": 1165
          },
          {
            "process": "msedge.exe with pid 6808"
          },
          {
            "type": "call",
            "pid": 6344,
            "cid": 1166
          },
          {
            "process": "msedge.exe with pid 6824"
          },
          {
            "type": "call",
            "pid": 6344,
            "cid": 1167
          },
          {
            "process": "svchost.exe with pid 7060"
          },
          {
            "type": "call",
            "pid": 6344,
            "cid": 1168
          },
          {
            "process": "dllhost.exe with pid 5564"
          },
          {
            "type": "call",
            "pid": 6344,
            "cid": 1169
          },
          {
            "process": "svchost.exe with pid 552"
          },
          {
            "type": "call",
            "pid": 6344,
            "cid": 1170
          },
          {
            "process": "msedge.exe with pid 3232"
          },
          {
            "type": "call",
            "pid": 6344,
            "cid": 1171
          },
          {
            "process": "msedge.exe with pid 7332"
          },
          {
            "type": "call",
            "pid": 6344,
            "cid": 1172
          },
          {
            "process": "svchost.exe with pid 7492"
          },
          {
            "type": "call",
            "pid": 6344,
            "cid": 1173
          },
          {
            "process": "svchost.exe with pid 7564"
          },
          {
            "type": "call",
            "pid": 6344,
            "cid": 1174
          },
          {
            "process": "ApplicationFrameHost.exe with pid 8116"
          },
          {
            "type": "call",
            "pid": 6344,
            "cid": 1175
          },
          {
            "process": "WinStore.App.exe with pid 8140"
          },
          {
            "type": "call",
            "pid": 6344,
            "cid": 1176
          },
          {
            "process": "RuntimeBroker.exe with pid 7396"
          },
          {
            "type": "call",
            "pid": 6344,
            "cid": 1177
          },
          {
            "process": "svchost.exe with pid 828"
          },
          {
            "type": "call",
            "pid": 6344,
            "cid": 1178
          },
          {
            "process": "audiodg.exe with pid 3476"
          },
          {
            "type": "call",
            "pid": 6344,
            "cid": 1179
          },
          {
            "process": "SkypeApp.exe with pid 532"
          },
          {
            "type": "call",
            "pid": 6344,
            "cid": 1180
          },
          {
            "process": "RuntimeBroker.exe with pid 1352"
          },
          {
            "type": "call",
            "pid": 6344,
            "cid": 1181
          },
          {
            "process": "SkypeBackgroundHost.exe with pid 2748"
          },
          {
            "type": "call",
            "pid": 6344,
            "cid": 1182
          },
          {
            "process": "svchost.exe with pid 3796"
          },
          {
            "type": "call",
            "pid": 6344,
            "cid": 1183
          },
          {
            "process": "svchost.exe with pid 4040"
          },
          {
            "type": "call",
            "pid": 6344,
            "cid": 1184
          },
          {
            "process": "svchost.exe with pid 8072"
          },
          {
            "type": "call",
            "pid": 6344,
            "cid": 1185
          },
          {
            "process": "svchost.exe with pid 5272"
          },
          {
            "type": "call",
            "pid": 6344,
            "cid": 1186
          },
          {
            "process": "svchost.exe with pid 7624"
          },
          {
            "type": "call",
            "pid": 6344,
            "cid": 1187
          },
          {
            "process": "SgrmBroker.exe with pid 6292"
          },
          {
            "type": "call",
            "pid": 6344,
            "cid": 1188
          },
          {
            "process": "svchost.exe with pid 388"
          },
          {
            "type": "call",
            "pid": 6344,
            "cid": 1189
          },
          {
            "process": "MoUsoCoreWorker.exe with pid 8092"
          },
          {
            "type": "call",
            "pid": 6344,
            "cid": 1190
          },
          {
            "process": "svchost.exe with pid 1452"
          },
          {
            "type": "call",
            "pid": 6344,
            "cid": 1191
          },
          {
            "process": "svchost.exe with pid 2068"
          },
          {
            "type": "call",
            "pid": 6344,
            "cid": 1192
          },
          {
            "process": "svchost.exe with pid 8508"
          },
          {
            "type": "call",
            "pid": 6344,
            "cid": 1193
          },
          {
            "process": "svchost.exe with pid 8516"
          },
          {
            "type": "call",
            "pid": 6344,
            "cid": 1194
          },
          {
            "process": "svchost.exe with pid 8568"
          },
          {
            "type": "call",
            "pid": 6344,
            "cid": 1195
          },
          {
            "process": "svchost.exe with pid 8636"
          },
          {
            "type": "call",
            "pid": 6344,
            "cid": 1196
          },
          {
            "process": "dasHost.exe with pid 8672"
          },
          {
            "type": "call",
            "pid": 6344,
            "cid": 1197
          },
          {
            "process": "upfc.exe with pid 1492"
          },
          {
            "type": "call",
            "pid": 6344,
            "cid": 1198
          },
          {
            "process": "CompatTelRunner.exe with pid 8928"
          },
          {
            "type": "call",
            "pid": 6344,
            "cid": 1199
          },
          {
            "process": "OneDriveStandaloneUpdater.exe with pid 1404"
          },
          {
            "type": "call",
            "pid": 6344,
            "cid": 1200
          },
          {
            "process": "OneDriveStandaloneUpdater.exe with pid 1272"
          },
          {
            "type": "call",
            "pid": 6344,
            "cid": 1201
          },
          {
            "process": "conhost.exe with pid 7880"
          },
          {
            "type": "call",
            "pid": 6344,
            "cid": 1202
          },
          {
            "process": "svchost.exe with pid 976"
          },
          {
            "type": "call",
            "pid": 6344,
            "cid": 1203
          },
          {
            "process": "rovwer.exe with pid 1224"
          },
          {
            "type": "call",
            "pid": 6344,
            "cid": 1204
          },
          {
            "process": "svchost.exe with pid 7996"
          },
          {
            "type": "call",
            "pid": 6344,
            "cid": 1205
          },
          {
            "process": "svchost.exe with pid 7776"
          },
          {
            "type": "call",
            "pid": 6344,
            "cid": 1206
          },
          {
            "process": "MicrosoftEdgeUpdate.exe with pid 6344"
          },
          {
            "type": "call",
            "pid": 6344,
            "cid": 1207
          }
        ],
        "new_data": [],
        "alert": false,
        "families": []
      },
      {
        "name": "process_interest",
        "description": "Expresses interest in specific running processes",
        "categories": [
          "generic"
        ],
        "severity": 2,
        "weight": 1,
        "confidence": 100,
        "references": [],
        "data": [
          {
            "type": "call",
            "pid": 6344,
            "cid": 1068
          },
          {
            "type": "call",
            "pid": 6344,
            "cid": 1069
          },
          {
            "type": "call",
            "pid": 6344,
            "cid": 1070
          },
          {
            "type": "call",
            "pid": 6344,
            "cid": 1071
          },
          {
            "type": "call",
            "pid": 6344,
            "cid": 1072
          },
          {
            "type": "call",
            "pid": 6344,
            "cid": 1073
          },
          {
            "type": "call",
            "pid": 6344,
            "cid": 1074
          },
          {
            "type": "call",
            "pid": 6344,
            "cid": 1075
          },
          {
            "type": "call",
            "pid": 6344,
            "cid": 1076
          },
          {
            "type": "call",
            "pid": 6344,
            "cid": 1077
          },
          {
            "type": "call",
            "pid": 6344,
            "cid": 1078
          },
          {
            "type": "call",
            "pid": 6344,
            "cid": 1079
          },
          {
            "type": "call",
            "pid": 6344,
            "cid": 1080
          },
          {
            "type": "call",
            "pid": 6344,
            "cid": 1081
          },
          {
            "type": "call",
            "pid": 6344,
            "cid": 1082
          },
          {
            "type": "call",
            "pid": 6344,
            "cid": 1083
          },
          {
            "type": "call",
            "pid": 6344,
            "cid": 1084
          },
          {
            "type": "call",
            "pid": 6344,
            "cid": 1085
          },
          {
            "type": "call",
            "pid": 6344,
            "cid": 1086
          },
          {
            "type": "call",
            "pid": 6344,
            "cid": 1087
          },
          {
            "type": "call",
            "pid": 6344,
            "cid": 1088
          },
          {
            "type": "call",
            "pid": 6344,
            "cid": 1089
          },
          {
            "type": "call",
            "pid": 6344,
            "cid": 1090
          },
          {
            "type": "call",
            "pid": 6344,
            "cid": 1091
          },
          {
            "type": "call",
            "pid": 6344,
            "cid": 1092
          },
          {
            "type": "call",
            "pid": 6344,
            "cid": 1093
          },
          {
            "type": "call",
            "pid": 6344,
            "cid": 1094
          },
          {
            "type": "call",
            "pid": 6344,
            "cid": 1095
          },
          {
            "type": "call",
            "pid": 6344,
            "cid": 1096
          },
          {
            "type": "call",
            "pid": 6344,
            "cid": 1097
          },
          {
            "type": "call",
            "pid": 6344,
            "cid": 1098
          },
          {
            "type": "call",
            "pid": 6344,
            "cid": 1099
          },
          {
            "type": "call",
            "pid": 6344,
            "cid": 1100
          },
          {
            "type": "call",
            "pid": 6344,
            "cid": 1101
          },
          {
            "type": "call",
            "pid": 6344,
            "cid": 1102
          },
          {
            "type": "call",
            "pid": 6344,
            "cid": 1103
          },
          {
            "type": "call",
            "pid": 6344,
            "cid": 1104
          },
          {
            "type": "call",
            "pid": 6344,
            "cid": 1105
          },
          {
            "type": "call",
            "pid": 6344,
            "cid": 1106
          },
          {
            "type": "call",
            "pid": 6344,
            "cid": 1107
          },
          {
            "type": "call",
            "pid": 6344,
            "cid": 1108
          },
          {
            "type": "call",
            "pid": 6344,
            "cid": 1109
          },
          {
            "type": "call",
            "pid": 6344,
            "cid": 1110
          },
          {
            "type": "call",
            "pid": 6344,
            "cid": 1111
          },
          {
            "type": "call",
            "pid": 6344,
            "cid": 1112
          },
          {
            "type": "call",
            "pid": 6344,
            "cid": 1113
          },
          {
            "type": "call",
            "pid": 6344,
            "cid": 1114
          },
          {
            "type": "call",
            "pid": 6344,
            "cid": 1115
          },
          {
            "type": "call",
            "pid": 6344,
            "cid": 1116
          },
          {
            "type": "call",
            "pid": 6344,
            "cid": 1117
          },
          {
            "type": "call",
            "pid": 6344,
            "cid": 1118
          },
          {
            "type": "call",
            "pid": 6344,
            "cid": 1119
          },
          {
            "type": "call",
            "pid": 6344,
            "cid": 1120
          },
          {
            "type": "call",
            "pid": 6344,
            "cid": 1121
          },
          {
            "type": "call",
            "pid": 6344,
            "cid": 1122
          },
          {
            "type": "call",
            "pid": 6344,
            "cid": 1123
          },
          {
            "type": "call",
            "pid": 6344,
            "cid": 1124
          },
          {
            "type": "call",
            "pid": 6344,
            "cid": 1125
          },
          {
            "type": "call",
            "pid": 6344,
            "cid": 1126
          },
          {
            "type": "call",
            "pid": 6344,
            "cid": 1127
          },
          {
            "type": "call",
            "pid": 6344,
            "cid": 1128
          },
          {
            "type": "call",
            "pid": 6344,
            "cid": 1129
          },
          {
            "type": "call",
            "pid": 6344,
            "cid": 1130
          },
          {
            "type": "call",
            "pid": 6344,
            "cid": 1131
          },
          {
            "type": "call",
            "pid": 6344,
            "cid": 1132
          },
          {
            "type": "call",
            "pid": 6344,
            "cid": 1133
          },
          {
            "type": "call",
            "pid": 6344,
            "cid": 1134
          },
          {
            "type": "call",
            "pid": 6344,
            "cid": 1135
          },
          {
            "type": "call",
            "pid": 6344,
            "cid": 1136
          },
          {
            "type": "call",
            "pid": 6344,
            "cid": 1137
          },
          {
            "type": "call",
            "pid": 6344,
            "cid": 1138
          },
          {
            "type": "call",
            "pid": 6344,
            "cid": 1139
          },
          {
            "type": "call",
            "pid": 6344,
            "cid": 1140
          },
          {
            "type": "call",
            "pid": 6344,
            "cid": 1141
          },
          {
            "type": "call",
            "pid": 6344,
            "cid": 1142
          },
          {
            "type": "call",
            "pid": 6344,
            "cid": 1143
          },
          {
            "type": "call",
            "pid": 6344,
            "cid": 1144
          },
          {
            "type": "call",
            "pid": 6344,
            "cid": 1145
          },
          {
            "type": "call",
            "pid": 6344,
            "cid": 1146
          },
          {
            "type": "call",
            "pid": 6344,
            "cid": 1147
          },
          {
            "type": "call",
            "pid": 6344,
            "cid": 1148
          },
          {
            "type": "call",
            "pid": 6344,
            "cid": 1149
          },
          {
            "type": "call",
            "pid": 6344,
            "cid": 1150
          },
          {
            "type": "call",
            "pid": 6344,
            "cid": 1151
          },
          {
            "type": "call",
            "pid": 6344,
            "cid": 1152
          },
          {
            "type": "call",
            "pid": 6344,
            "cid": 1153
          },
          {
            "type": "call",
            "pid": 6344,
            "cid": 1154
          },
          {
            "type": "call",
            "pid": 6344,
            "cid": 1155
          },
          {
            "type": "call",
            "pid": 6344,
            "cid": 1156
          },
          {
            "type": "call",
            "pid": 6344,
            "cid": 1157
          },
          {
            "type": "call",
            "pid": 6344,
            "cid": 1158
          },
          {
            "type": "call",
            "pid": 6344,
            "cid": 1159
          },
          {
            "type": "call",
            "pid": 6344,
            "cid": 1160
          },
          {
            "type": "call",
            "pid": 6344,
            "cid": 1161
          },
          {
            "type": "call",
            "pid": 6344,
            "cid": 1162
          },
          {
            "type": "call",
            "pid": 6344,
            "cid": 1163
          },
          {
            "type": "call",
            "pid": 6344,
            "cid": 1164
          },
          {
            "type": "call",
            "pid": 6344,
            "cid": 1165
          },
          {
            "type": "call",
            "pid": 6344,
            "cid": 1166
          },
          {
            "type": "call",
            "pid": 6344,
            "cid": 1167
          },
          {
            "type": "call",
            "pid": 6344,
            "cid": 1168
          },
          {
            "type": "call",
            "pid": 6344,
            "cid": 1169
          },
          {
            "type": "call",
            "pid": 6344,
            "cid": 1170
          },
          {
            "type": "call",
            "pid": 6344,
            "cid": 1171
          },
          {
            "type": "call",
            "pid": 6344,
            "cid": 1172
          },
          {
            "type": "call",
            "pid": 6344,
            "cid": 1173
          },
          {
            "type": "call",
            "pid": 6344,
            "cid": 1174
          },
          {
            "type": "call",
            "pid": 6344,
            "cid": 1175
          },
          {
            "type": "call",
            "pid": 6344,
            "cid": 1176
          },
          {
            "type": "call",
            "pid": 6344,
            "cid": 1177
          },
          {
            "type": "call",
            "pid": 6344,
            "cid": 1178
          },
          {
            "type": "call",
            "pid": 6344,
            "cid": 1179
          },
          {
            "type": "call",
            "pid": 6344,
            "cid": 1180
          },
          {
            "type": "call",
            "pid": 6344,
            "cid": 1181
          },
          {
            "type": "call",
            "pid": 6344,
            "cid": 1182
          },
          {
            "type": "call",
            "pid": 6344,
            "cid": 1183
          },
          {
            "type": "call",
            "pid": 6344,
            "cid": 1184
          },
          {
            "type": "call",
            "pid": 6344,
            "cid": 1185
          },
          {
            "type": "call",
            "pid": 6344,
            "cid": 1186
          },
          {
            "type": "call",
            "pid": 6344,
            "cid": 1187
          },
          {
            "type": "call",
            "pid": 6344,
            "cid": 1188
          },
          {
            "type": "call",
            "pid": 6344,
            "cid": 1189
          },
          {
            "type": "call",
            "pid": 6344,
            "cid": 1190
          },
          {
            "type": "call",
            "pid": 6344,
            "cid": 1191
          },
          {
            "type": "call",
            "pid": 6344,
            "cid": 1192
          },
          {
            "type": "call",
            "pid": 6344,
            "cid": 1193
          },
          {
            "type": "call",
            "pid": 6344,
            "cid": 1194
          },
          {
            "type": "call",
            "pid": 6344,
            "cid": 1195
          },
          {
            "type": "call",
            "pid": 6344,
            "cid": 1196
          },
          {
            "type": "call",
            "pid": 6344,
            "cid": 1197
          },
          {
            "type": "call",
            "pid": 6344,
            "cid": 1198
          },
          {
            "type": "call",
            "pid": 6344,
            "cid": 1199
          },
          {
            "type": "call",
            "pid": 6344,
            "cid": 1200
          },
          {
            "type": "call",
            "pid": 6344,
            "cid": 1201
          },
          {
            "type": "call",
            "pid": 6344,
            "cid": 1202
          },
          {
            "type": "call",
            "pid": 6344,
            "cid": 1203
          },
          {
            "type": "call",
            "pid": 6344,
            "cid": 1204
          },
          {
            "type": "call",
            "pid": 6344,
            "cid": 1205
          },
          {
            "type": "call",
            "pid": 6344,
            "cid": 1206
          },
          {
            "type": "call",
            "pid": 6344,
            "cid": 1207
          },
          {
            "process": "MicrosoftEdgeUpdate.exe"
          }
        ],
        "new_data": [],
        "alert": false,
        "families": []
      },
      {
        "name": "antisandbox_unhook",
        "description": "Tries to unhook or modify Windows functions monitored by CAPE",
        "categories": [
          "anti-sandbox"
        ],
        "severity": 3,
        "weight": 1,
        "confidence": 60,
        "references": [],
        "data": [
          {
            "type": "call",
            "pid": 6344,
            "cid": 1239
          },
          {
            "type": "call",
            "pid": 6344,
            "cid": 1240
          },
          {
            "type": "call",
            "pid": 6344,
            "cid": 1241
          },
          {
            "type": "call",
            "pid": 6344,
            "cid": 1242
          },
          {
            "type": "call",
            "pid": 6344,
            "cid": 1243
          },
          {
            "type": "call",
            "pid": 6344,
            "cid": 1244
          },
          {
            "type": "call",
            "pid": 6344,
            "cid": 1245
          },
          {
            "type": "call",
            "pid": 6344,
            "cid": 1246
          },
          {
            "type": "call",
            "pid": 6344,
            "cid": 1247
          },
          {
            "type": "call",
            "pid": 6344,
            "cid": 1248
          },
          {
            "type": "call",
            "pid": 6344,
            "cid": 1249
          },
          {
            "type": "call",
            "pid": 6344,
            "cid": 1250
          },
          {
            "type": "call",
            "pid": 6344,
            "cid": 1251
          },
          {
            "type": "call",
            "pid": 6344,
            "cid": 1252
          },
          {
            "unhook": "function_name: CryptHashData, type: removal"
          },
          {
            "unhook": "function_name: CryptCreateHash, type: removal"
          },
          {
            "unhook": "function_name: CryptAcquireContextA, type: removal"
          },
          {
            "unhook": "function_name: CryptEncrypt, type: removal"
          },
          {
            "unhook": "function_name: CryptHashSessionKey, type: removal"
          },
          {
            "unhook": "function_name: CryptAcquireContextW, type: removal"
          },
          {
            "unhook": "function_name: CryptDecrypt, type: removal"
          },
          {
            "unhook": "function_name: CryptEnumProvidersW, type: removal"
          },
          {
            "unhook": "function_name: VarBstrCat, type: removal"
          },
          {
            "unhook": "function_name: CryptImportKey, type: removal"
          },
          {
            "unhook": "function_name: CryptExportKey, type: removal"
          },
          {
            "unhook": "function_name: CryptGenKey, type: removal"
          },
          {
            "unhook": "function_name: CryptEnumProvidersA, type: removal"
          },
          {
            "unhook": "function_name: CryptGenRandom, type: removal"
          }
        ],
        "new_data": [],
        "alert": false,
        "families": []
      }
    ],
    "failure_reason": null,
    "improvement_suggestions": [],
    "debugger_log": null,
    "raw_response": "## Step 1: Identify suspicious instructions and extract them\n\n- Conditional jumps (JE, JNE, JZ, JNZ, etc.)\n- Test/compare instructions (TEST, CMP)\n- Function calls (CALL)\n\n**Suspicious Instructions:**\n\n* JE at address 0041B90E\n* TEST AL, 01h at address 0041B91C\n* CALL dword ptr [0042F13Ch] at address 0041B923\n* CALL dword ptr [0042F140h] at address 0041B92A\n\n**Step 2: Trace the exit path backwards to understand evasion**\n\nStarting from the exit (0041B93C), trace backwards:\n\n- The instruction that directly causes the exit is `FF15A0F14200` at address 0041B93C.\n- The conditional jump leading to this path is not directly related, but it seems like a loop or repetition because of similar code in both traces.\n- The check determining the jump's direction is unclear without more information.\n\n**Step 3: Select different bypass candidates**\n\nChoose 3 DIFFERENT instructions that could potentially be used for evasion:\n\n1. `JE` at address 0041B90E\n2. `TEST AL, 01h` at address 0041B91C\n3. `CALL dword ptr [0042F13Ch]` at address 0041B923\n\n**Step 4: Build patterns (6-20 bytes each)**\n\nCombine each candidate with adjacent instructions to create a specific pattern:\n\n1. **Pattern 1:** Combine JE, TEST, and CALL instructions\n```\n74 20 85 C0 0F 84 ?? ?? ?? ?? E8 F7 25 00 00\n```\n\n2. **Pattern 2:** Combine TEST AL, 01h with MOV EAX instruction\n```\nA8 01 8B 45 ?? FF 15 A0 F1 42 00\n```\n\n3. **Pattern 3:** Combine CALL dword ptr [0042F13Ch] with PUSH EAX and POP ECX instructions\n```\nFF 15 CF 14 20 00 50 FF 35 C0 F1 42 00\n```\n\n**Step 5: Apply wildcards and generate the YARA rule**\n\nReplace address/offset bytes with `??`:\n\n```yara\nrule Bypass_Sample\n{\n    meta:\n        description = \"Evasion bypass rule\"\n        cape_options = \"bp0=$pattern0+0,action0=skip,bp1=$pattern1+0,action1=skip,bp2=$pattern2+0,action2=skip,count=0\"\n\n    strings:\n        $pattern0 = { [6-20 bytes with wildcards] 74 20 85 C0 0F 84 ?? ?? ?? ?? E8 F7 25 00 00 }\n        $pattern1 = { [6-20 bytes - DIFFERENT sequence] A8 01 8B 45 ?? FF 15 A0 F1 42 00 }\n        $pattern2 = { [6-20 bytes - DIFFERENT sequence] FF 15 CF 14 20 00 50 FF 35 C0 F1 42 00 }\n\n    condition:\n        any of them\n}\n```",
    "yara_file": "ablation_results\\llama3.1_8b\\Iter\\Iter\\8cd1795a98c9fc8a\\iter0_v1.yar"
  },
  "best_score": 4,
  "optimization_history": [
    "Iteration 1: SUCCESS - 4 new signatures"
  ],
  "successful_patterns": [
    ""
  ],
  "failed_patterns": []
}